Workbook

Sheet PV
A1: Database | B1: PV
A3: Activity | B3: 1,1-difluoroethane production, HFC-152a
A4: comment | B4: Basic inventory based on cumulative data. Pre-products, energy use, infrastructure, some air emissions and transports. No full information on all air and water emissions available. Location: Production plant of DuPont in the United States. Technology: Fluoropolymer chemistry. Time period: Time of publications. Production volume: Not known Sampling: Publication of cumulative data. Extrapolations: Desaggregation of published cumulative results for global warming potential and cumulative energy demand. Uncertainty: None
A5: location | B5: US
A6: production amount | B6: 1
A7: reference product | B7: 1,1-difluoroethane, HFC-152a
A8: source | B8: Fthenakis, V., Leccisi, E., & Frischknecht, Rolf; Stolz, Philippe; Krebs, Luana; de Wild-Scholten, Mariska; Sinha, P. (2021). Life Cycle Inventories and Life Cycle Assessments of Photovoltaic Systems 2020 Task 12 PV Sustainability. Progress in Photovoltaics: Research and Applications, 29(10), 1068–1077. www.iea-pvps.org
A9: type | B9: process
A10: unit | B10: kilogram
A11: Exchanges
A12: name | B12: amount | C12: location | D12: unit | E12: categories | F12: type | G12: uncertainty type | H12: loc | I12: scale | J12: comment | K12: negative | L12: reference product
A13: Ethane, 1,1-difluoro-, HFC-152a | B13: 0.013583 | D13: kilogram | E13: air::urban air close to ground | F13: biosphere | G13: 2 | H13: -4.2989363 | I13: 0.30183001 | J13: (5,3,1,1,1,5); Rough estimation based on cumulative data, Krieger et al. 2006
A14: Heat, waste | B14: 3.92 | D14: megajoule | E14: air | F14: biosphere | G14: 2 | H14: 1.3660917 | I14: 0.22493235 | J14: (5,3,1,1,1,5); Rough estimation based on cumulative data, Krieger et al. 2006
A15: 1,1-difluoroethane production, HFC-152a | B15: 1 | C15: US | D15: kilogram | E15: chemicals::organics | F15: production | G15: 0 | H15: 1 | L15: 1,1-difluoroethane, HFC-152a
A16: acetylene production | B16: 0.42733 | C16: RER | D16: kilogram | F16: technosphere | G16: 2 | H16: -0.85019873 | I16: 0.22493235 | J16: (5,3,1,1,1,5); Acetylen yield is 92.4% | L16: acetylene
A17: chemical factory construction, organics | B17: 4e-10 | C17: RER | D17: unit | F17: technosphere | G17: 2 | H17: -21.639557 | I17: 0.59308259 | J17: (5,3,1,1,1,5); Rough estimation based on cumulative data, Krieger et al. 2006 | L17: chemical factory, organics
A18: heat production, natural gas, at industrial furnace >100kW | B18: 0.98 | C18: Europe without Switzerland | D18: megajoule | F18: technosphere | G18: 2 | H18: -0.020202707 | I18: 0.22493235 | J18: (5,3,1,1,1,5); Rough estimation based on cumulative data, Krieger et al. 2006 | L18: heat, district or industrial, natural gas
A19: hydrogen fluoride production | B19: 0.63699 | C19: GLO | D19: kilogram | F19: technosphere | G19: 2 | H19: -0.45100132 | I19: 0.22493235 | J19: (5,3,1,1,1,5); Rough estimation based on cumulative data, Krieger et al. 2006 | L19: hydrogen fluoride
A20: lime production, hydrated, packed | B20: 0.021387 | C20: CH | D20: kilogram | F20: technosphere | G20: 2 | H20: -3.844972 | I20: 0.22493235 | J20: (5,3,1,1,1,5); Rough estimation based on cumulative data, Krieger et al. 2006 | L20: lime, hydrated, packed
A21: market for electricity, medium voltage | B21: 1.0889 | C21: RS | D21: kilowatt hour | F21: technosphere | G21: 2 | H21: 0.085168012 | I21: 0.22493235 | J21: (5,3,1,1,1,5); Rough estimation based on cumulative data, Krieger et al. 2006 | L21: electricity, medium voltage
A22: market for transport, freight, sea, container ship | B22: 6.3699 | C22: GLO | D22: ton kilometer | F22: technosphere | G22: 2 | H22: 1.8515838 | I22: 0.41246039 | J22: (5,3,1,1,1,5); Rough estimation based on cumulative data, Krieger et al. 2006 | L22: transport, freight, sea, container ship
A23: market for zinc | B23: 0.0019676 | C23: GLO | D23: kilogram | F23: technosphere | G23: 2 | H23: -6.2309408 | I23: 0.22493235 | J23: (5,3,1,1,1,5); Rough estimation based on cumulative data, Krieger et al. 2006 | L23: zinc
A24: transport, freight train, diesel | B24: 0.27041 | C24: Europe without Switzerland | D24: ton kilometer | F24: technosphere | G24: 2 | H24: -1.307816 | I24: 0.41246039 | J24: (5,3,1,1,1,5); Rough estimation based on cumulative data, Krieger et al. 2006 | L24: transport, freight train
A25: transport, freight, lorry 7.5-16 metric ton, EURO4 | B25: 0.10877 | C25: RER | D25: ton kilometer | F25: technosphere | G25: 2 | H25: -2.2185197 | I25: 0.41246039 | J25: (5,3,1,1,1,5); Rough estimation based on cumulative data, Krieger et al. 2006 | L25: transport, freight, lorry 7.5-16 metric ton, EURO4
A27: Activity | B27: photovoltaic slanted-roof installation, 1.3 MWp, multi-Si, panel, mounted, on roof
A28: comment | B28: Photovoltaic installation with a capacity of 1300kWp and a life time of 30 years installed in Switzerland. The efficiency of multi-Si PV modules is 16.8% (Fraunhofer ISE Photovoltaics Report 2019). The share of rejected or replaced PV modules is estimated at 3%. The inverter is assumed to be replaced once during the service life of the PV system. All components (modules, mounting system, electric installation, inverter) for the installation of a 1300 kWp photovoltaic plant, energy use for the mounting, transport of materials to the place of installation. Disposal of components after end of life. Location: Installation in CH Technology: Current technology for mounting of panels or laminates, electric installations and other components. Sampling: Questionnaire filled in by the engineer of the plant (Hostettler). Extrapolations: none Uncertainty: none
A29: location | B29: CH
A30: production amount | B30: 1
A31: reference product | B31: photovoltaic slanted-roof installation, 1.3 MWp, multi-Si, panel, mounted, on roof
A32: source | B32: Fthenakis, V., Leccisi, E., & Frischknecht, Rolf; Stolz, Philippe; Krebs, Luana; de Wild-Scholten, Mariska; Sinha, P. (2021). Life Cycle Inventories and Life Cycle Assessments of Photovoltaic Systems 2020 Task 12 PV Sustainability. Progress in Photovoltaics: Research and Applications, 29(10), 1068–1077. www.iea-pvps.org
A33: type | B33: process
A34: unit | B34: unit
A35: Exchanges
A36: name | B36: amount | C36: location | D36: unit | E36: categories | F36: type | G36: uncertainty type | H36: loc | I36: scale | J36: comment | K36: negative | L36: reference product
A37: Heat, waste | B37: 371.5 | D37: megajoule | E37: air::urban air close to ground | F37: biosphere | G37: 2 | H37: 5.9175489 | I37: 0.36098878 | J37: (1,na,na,na,na,na); calculated with electricity use
A38: photovoltaic slanted-roof installation, 1.3 MWp, multi-Si, panel, mounted, on roof | B38: 1 | C38: CH | D38: unit | E38: Electricity by fuel::Photovoltaic\Infrastructure | F38: production | G38: 0 | H38: 1 | L38: photovoltaic slanted-roof installation, 1.3 MWp, multi-Si, panel, mounted, on roof
A39: electric installation, 1.3 MWp photovoltaic plant, at plant | B39: 1 | C39: CH | D39: unit | F39: technosphere | G39: 2 | H39: 0 | I39: 0.74824658 | J39: (3,4,1,1,1,5);
A40: inverter production, 500kW | B40: 4.4132 | C40: RER | D40: unit | F40: technosphere | G40: 2 | H40: 1.4846 | I40: 0.74824658 | J40: (2,4,1,1,1,5); 1 replacement in the life time | L40: inverter, 500kW
A41: market for electricity, low voltage | B41: 103.19 | C41: CH | D41: kilowatt hour | F41: technosphere | G41: 2 | H41: 4.6365719 | I41: 0.5093334 | J41: (3,4,3,1,1,5); scaled from a 3kWp plant over capacity | L41: electricity, low voltage
A42: photovoltaic panel, multi-Si, at regional storage | B42: 7438.9 | C42: RER | D42: square meter | F42: technosphere | G42: 2 | H42: 8.9144783 | I42: 0.74824658 | J42: (3,4,1,1,1,5); calculation with maximum power output and module efficiency; 2% of modules replaced in the life time, 1% rejects
A43: slanted-roof construction, mounted, on roof, Stade de Suisse | B43: 7222.2 | C43: CH | D43: square meter | F43: technosphere | G43: 2 | H43: 8.8849149 | I43: 0.74824658 | J43: (3,4,1,1,1,5); calculation with maximum power output and module efficiency
A44: transport, freight, lorry 7.5-16 metric ton, EURO4 | B44: 13765 | C44: RER | D44: ton kilometer | F44: technosphere | G44: 2 | H44: 9.5298844 | I44: 0.54701758 | J44: (4,5,na,na,na,na); 100km for transport of modules, substructure, electric installation and inverters to the place of installation | L44: transport, freight, lorry 7.5-16 metric ton, EURO4
A45: treatment, c-Si PV module | B45: 98155 | C45: RER | D45: kilogram | F45: technosphere | G45: 2 | H45: 11.494303 | I45: 0.50864688 | J45: (3,4,1,1,1,5); recycling of PV modules at the end of life
A47: Activity | B47: photovoltaic flat-roof installation, 156 kWp, multi-Si, on roof
A48: comment | B48: Photovoltaic installation with a capacity of 156kWp and a life time of 30 years installed in Switzerland. The efficiency of multi-Si PV modules is 16.8% (Fraunhofer ISE Photovoltaics Report 2019). The share of rejected or replaced PV modules is estimated at 3%. The inverter is assumed to be replaced once during the service life of the PV system. All components (modules, mounting system, electric installation, inverter) for the installation of a 156 kWp photovoltaic plant, energy use for the mounting, transport of materials to the place of installation. Disposal of components after end of life. Location: Installation in CH Technology: Current technology for mounting of panels or laminates, electric installations and other components. Sampling: Questionnaire filled in by the operator of the plant (Edisun Power AG). Extrapolations: none Uncertainty: none
A49: location | B49: CH
A50: production amount | B50: 1
A51: reference product | B51: photovoltaic flat-roof installation, 156 kWp, multi-Si, on roof
A52: source | B52: Fthenakis, V., Leccisi, E., & Frischknecht, Rolf; Stolz, Philippe; Krebs, Luana; de Wild-Scholten, Mariska; Sinha, P. (2021). Life Cycle Inventories and Life Cycle Assessments of Photovoltaic Systems 2020 Task 12 PV Sustainability. Progress in Photovoltaics: Research and Applications, 29(10), 1068–1077. www.iea-pvps.org
A53: type | B53: process
A54: unit | B54: unit
A55: Exchanges
A56: name | B56: amount | C56: location | D56: unit | E56: categories | F56: type | G56: uncertainty type | H56: loc | I56: scale | J56: comment | K56: negative | L56: reference product
A57: Heat, waste | B57: 42.99 | D57: megajoule | E57: air::urban air close to ground | F57: biosphere | G57: 2 | H57: 3.7609675 | I57: 0.034483102 | J57: (1,na,na,na,na,na); calculated with electricity use
A58: photovoltaic flat-roof installation, 156 kWp, multi-Si, on roof | B58: 1 | C58: CH | D58: unit | E58: Electricity by fuel::Photovoltaic\Infrastructure | F58: production | G58: 0 | H58: 1 | L58: photovoltaic flat-roof installation, 156 kWp, multi-Si, on roof
A59: electric installation, 156 kWp photovoltaic plant, at plant | B59: 1 | C59: CH | D59: unit | F59: technosphere | G59: 2 | H59: 0 | I59: 0.92753143 | J59: (3,4,1,1,1,5);
A60: inverter production, 500kW | B60: 1.0498 | C60: RER | D60: unit | F60: technosphere | G60: 2 | H60: 0.04859967 | I60: 0.92753143 | J60: (2,4,1,1,1,5); 1 replacement in the life time | L60: inverter, 500kW
A61: market for electricity, low voltage | B61: 11.942 | C61: CH | D61: kilowatt hour | F61: technosphere | G61: 2 | H61: 2.4800616 | I61: 0.5093334 | J61: (3,4,3,1,1,5); scaled from a 3kWp plant over capacity | L61: electricity, low voltage
A62: photovoltaic mounting system production, for flat-roof installation | B62: 866.67 | C62: RER | D62: square meter | F62: technosphere | G62: 2 | H62: 6.7646583 | I62: 0.92753143 | J62: (3,4,1,1,1,5); calculation with maximum power output and module efficiency | L62: photovoltaic mounting system, for flat-roof installation
A63: photovoltaic panel, multi-Si, at regional storage | B63: 892.67 | C63: RER | D63: square meter | F63: technosphere | G63: 2 | H63: 6.794217 | I63: 0.92753143 | J63: (3,4,1,1,1,5); calculation with maximum power output and module efficiency; 2% of modules replaced in the life time, 1% rejects
A64: transport, freight, lorry 7.5-16 metric ton, EURO4 | B64: 1966.6 | C64: RER | D64: ton kilometer | F64: technosphere | G64: 2 | H64: 7.5840614 | I64: 0.58227804 | J64: (4,5,na,na,na,na); 100km for transport of modules, substructure, electric installation and inverters to the place of installation | L64: transport, freight, lorry 7.5-16 metric ton, EURO4
A65: treatment, c-Si PV module | B65: 11779 | C65: RER | D65: kilogram | F65: technosphere | G65: 2 | H65: 9.3740736 | I65: 0.50797753 | J65: (3,4,1,1,1,5); recycling of PV modules at the end of life
A67: Activity | B67: photovoltaic flat-roof installation, 156 kWp, single-Si, on roof
A68: comment | B68: Photovoltaic installation with a capacity of 156kWp and a life time of 30 years installed in Switzerland. The efficiency of single-Si PV modules is 17.9% (Fraunhofer ISE Photovoltaics Report 2019). The share of rejected or replaced PV modules is estimated at 3%. The inverter is assumed to be replaced once during the service life of the PV system. All components (modules, mounting system, electric installation, inverter) for the installation of a 156 kWp photovoltaic plant, energy use for the mounting, transport of materials to the place of installation. Disposal of components after end of life. Location: Installation in CH Technology: Current technology for mounting of panels or laminates, electric installations and other components. Sampling: Questionnaire filled in by the operator of the plant (Edisun Power AG). Extrapolations: none Uncertainty: none
A69: location | B69: CH
A70: production amount | B70: 1
A71: reference product | B71: photovoltaic flat-roof installation, 156 kWp, single-Si, on roof
A72: source | B72: Fthenakis, V., Leccisi, E., & Frischknecht, Rolf; Stolz, Philippe; Krebs, Luana; de Wild-Scholten, Mariska; Sinha, P. (2021). Life Cycle Inventories and Life Cycle Assessments of Photovoltaic Systems 2020 Task 12 PV Sustainability. Progress in Photovoltaics: Research and Applications, 29(10), 1068–1077. www.iea-pvps.org
A73: type | B73: process
A74: unit | B74: unit
A75: Exchanges
A76: name | B76: amount | C76: location | D76: unit | E76: categories | F76: type | G76: uncertainty type | H76: loc | I76: scale | J76: comment | K76: negative | L76: reference product
A77: Heat, waste | B77: 42.99 | D77: megajoule | E77: air::urban air close to ground | F77: biosphere | G77: 2 | H77: 3.7609675 | I77: 0.034483102 | J77: (1,na,na,na,na,na); calculated with electricity use
A78: photovoltaic flat-roof installation, 156 kWp, single-Si, on roof | B78: 1 | C78: CH | D78: unit | E78: Electricity by fuel::Photovoltaic\Infrastructure | F78: production | G78: 0 | H78: 1 | L78: photovoltaic flat-roof installation, 156 kWp, single-Si, on roof
A79: electric installation, 156 kWp photovoltaic plant, at plant | B79: 1 | C79: CH | D79: unit | F79: technosphere | G79: 2 | H79: 0 | I79: 0.92753143 | J79: (3,4,1,1,1,5);
A80: inverter production, 500kW | B80: 1.0498 | C80: RER | D80: unit | F80: technosphere | G80: 2 | H80: 0.04859967 | I80: 0.92753143 | J80: (2,4,1,1,1,5); 1 replacement in the life time | L80: inverter, 500kW
A81: market for electricity, low voltage | B81: 11.942 | C81: CH | D81: kilowatt hour | F81: technosphere | G81: 2 | H81: 2.4800616 | I81: 0.5093334 | J81: (3,4,3,1,1,5); scaled from a 3kWp plant over capacity | L81: electricity, low voltage
A82: photovoltaic mounting system production, for flat-roof installation | B82: 800 | C82: RER | D82: square meter | F82: technosphere | G82: 2 | H82: 6.6846117 | I82: 0.92753143 | J82: (3,4,1,1,1,5); calculation with maximum power output and module efficiency | L82: photovoltaic mounting system, for flat-roof installation
A83: photovoltaic panel, single-Si, at regional storage | B83: 824 | C83: RER | D83: square meter | F83: technosphere | G83: 2 | H83: 6.7141705 | I83: 0.92753143 | J83: (3,4,1,1,1,5); calculation with maximum power output and module efficiency; 2% of modules replaced in the life time, 1% rejects
A84: transport, freight, lorry 7.5-16 metric ton, EURO4 | B84: 1840.7 | C84: RER | D84: ton kilometer | F84: technosphere | G84: 2 | H84: 7.5179012 | I84: 0.58227804 | J84: (4,5,na,na,na,na); 100km for transport of modules, substructure, electric installation and inverters to the place of installation | L84: transport, freight, lorry 7.5-16 metric ton, EURO4
A85: treatment, c-Si PV module | B85: 10836 | C85: RER | D85: kilogram | F85: technosphere | G85: 2 | H85: 9.2906292 | I85: 0.50797753 | J85: (3,4,1,1,1,5); recycling of PV modules at the end of life
A87: Activity | B87: photovoltaic flat-roof installation, 280 kWp, multi-Si, on roof
A88: comment | B88: Photovoltaic installation with a capacity of 280kWp and a life time of 30 years installed in Switzerland. The efficiency of multi-Si PV modules is 16.8% (Fraunhofer ISE Photovoltaics Report 2019). The share of rejected or replaced PV modules is estimated at 3%. The inverter is assumed to be replaced once during the service life of the PV system. All components (modules, mounting system, electric installation, inverter) for the installation of a 280 kWp photovoltaic plant, energy use for the mounting, transport of materials to the place of installation. Disposal of components after end of life. Location: Installation in CH Technology: Current technology for mounting of panels or laminates, electric installations and other components. Sampling: Publication of plant specific (partly aggregated) data and literature information. Extrapolations: none Uncertainty: none
A89: location | B89: CH
A90: production amount | B90: 1
A91: reference product | B91: photovoltaic flat-roof installation, 280 kWp, multi-Si, on roof
A92: source | B92: Fthenakis, V., Leccisi, E., & Frischknecht, Rolf; Stolz, Philippe; Krebs, Luana; de Wild-Scholten, Mariska; Sinha, P. (2021). Life Cycle Inventories and Life Cycle Assessments of Photovoltaic Systems 2020 Task 12 PV Sustainability. Progress in Photovoltaics: Research and Applications, 29(10), 1068–1077. www.iea-pvps.org
A93: type | B93: process
A94: unit | B94: unit
A95: Exchanges
A96: name | B96: amount | C96: location | D96: unit | E96: categories | F96: type | G96: uncertainty type | H96: loc | I96: scale | J96: comment | K96: negative | L96: reference product
A97: Heat, waste | B97: 77.28 | D97: megajoule | E97: air::urban air close to ground | F97: biosphere | G97: 2 | H97: 4.3474352 | I97: 0.36098878 | J97: (1,na,na,na,na,na); calculated with electricity use
A98: photovoltaic flat-roof installation, 280 kWp, multi-Si, on roof | B98: 1 | C98: CH | D98: unit | E98: Electricity by fuel::Photovoltaic\Infrastructure | F98: production | G98: 0 | H98: 1 | L98: photovoltaic flat-roof installation, 280 kWp, multi-Si, on roof
A99: electric installation, 280 kWp photovoltaic plant, at plant | B99: 1 | C99: CH | D99: unit | F99: technosphere | G99: 2 | H99: 0 | I99: 0.74824658 | J99: (3,4,1,1,1,5);
A100: inverter production, 500kW | B100: 1.6182 | C100: RER | D100: unit | F100: technosphere | G100: 2 | H100: 0.48131442 | I100: 0.74824658 | J100: (2,4,1,1,1,5); 1 replacement in the life time | L100: inverter, 500kW
A101: market for electricity, low voltage | B101: 21.467 | C101: CH | D101: kilowatt hour | F101: technosphere | G101: 2 | H101: 3.0665169 | I101: 0.5093334 | J101: (3,4,3,1,1,5); scaled from a 3kWp plant over capacity | L101: electricity, low voltage
A102: photovoltaic mounting system production, for flat-roof installation | B102: 1555.6 | C102: RER | D102: square meter | F102: technosphere | G102: 2 | H102: 7.3496166 | I102: 0.74824658 | J102: (3,4,1,1,1,5); calculation with maximum power output and module efficiency | L102: photovoltaic mounting system, for flat-roof installation
A103: photovoltaic panel, multi-Si, at regional storage | B103: 1602.2 | C103: RER | D103: square meter | F103: technosphere | G103: 2 | H103: 7.379133 | I103: 0.74824658 | J103: (3,4,1,1,1,5); calculation with maximum power output and module efficiency; 2% of modules replaced in the life time, 1% rejects
A104: transport, freight, lorry 7.5-16 metric ton, EURO4 | B104: 3406.2 | C104: RER | D104: ton kilometer | F104: technosphere | G104: 2 | H104: 8.1333526 | I104: 0.54701758 | J104: (4,5,na,na,na,na); 100km for transport of modules, substructure, electric installation and inverters to the place of installation | L104: transport, freight, lorry 7.5-16 metric ton, EURO4
A105: treatment, c-Si PV module | B105: 21141 | C105: RER | D105: kilogram | F105: technosphere | G105: 2 | H105: 9.9589696 | I105: 0.50864688 | J105: (3,4,1,1,1,5); recycling of PV modules at the end of life
...

Sheet PV (extension)
A1: Activity | B1: electricity production, photovoltaic, residential
A2: comment | B2: =_xlfn._LONGTEXT("Dataset created adapted from the methodology followed by: Life Cycle Inventories and Life Cycle Assessments of Photovoltaic Systems 2020 Task 12 PV Sustainability, December 2020, DOI: 10.13140/RG.2.2.17977.19041 However, the technology split is not countr","y-specific but based based on weighted average of OECD countries. Production volume provided by IRENA 2025: https://www.irena.org/Publications/2025/Jul/Renewable-energy-statistics-2025 Open-ground PV panel productivity in the country based on area-weighte","d estimate from the Global Solar Atlas: https://globalsolaratlas.info/download/world The lifetime of PV systems is estimated at 30 years based on the PEFCR PV electricity. Production mix of photovoltaic electricity in the country. Annual output, Roof-Top",": ")&HLOOKUP(B3,parameters!$C$195:$EJ$198,2,0)&" kWh/kWp. Annual output, Facade: "&HLOOKUP(B3,parameters!$C$195:$EJ$198,3,0)&" kWh/kWp. Annual output, Open-ground: "&HLOOKUP(B3,parameters!$C$195:$EJ$198,4,0)&_xlfn._LONGTEXT(" kWh/kWp. Amount of solar energy transformed to electricity. Waste heat emission due to losses of electricity in the system. Technology: Electricity production with grid-connected photovoltaic power plants. Time period: Time of publications Production v","olume: ")&VLOOKUP(B3,'extension - production vol'!$B$6:$D$235,3,0)&_xlfn._LONGTEXT(" GWh in 2025. Sampling: Statistical data and model calculations Extrapolations: Use of PV technology data investigated for other countries (Switzerland). Correction of average yield with Swiss data. Uncertainty: None Author: Romain Sacchi, PSI, romain.","sacchi@psi.ch") -> Dataset created adapted from the methodology followed by: Life Cycle Inventories and Life Cycle Assessments of Photovoltaic Systems 2020 Task 12 PV Sustainability, December 2020, DOI: 10.13140/RG.2.2.17977.19041 However, the technology split is not country-specific but based based on weighted average of OECD countries. Production volume provided by IRENA 2025: https://www.irena.org/Publications/2025/Jul/Renewable-energy-statistics-2025 Open-ground PV panel productivity in the country based on area-weighted estimate from the Global Solar Atlas: https://globalsolaratlas.info/download/world The lifetime of PV systems is estimated at 30 years based on the PEFCR PV electricity. Production mix of photovoltaic electricity in the country. Annual output, Roof-Top: 1860.26870229946 kWh/kWp. Annual output, Facade: 1306.14611012515 kWh/kWp. Annual output, Open-ground: 1979.00925776538 kWh/kWp. Amount of solar energy transformed to electricity. Waste heat emission due to losses of electricity in the system. Technology: Electricity production with grid-connected photovoltaic power plants. Time period: Time of publications Production volume: 13.901 GWh in 2025. Sampling: Statistical data and model calculations Extrapolations: Use of PV technology data investigated for other countries (Switzerland). Correction of average yield with Swiss data. Uncertainty: None Author: Romain Sacchi, PSI, romain.sacchi@psi.ch
A3: location | B3: NA
A4: production amount | B4: 1
A5: reference product | B5: electricity, low voltage
A6: source | B6: Fthenakis, V., Leccisi, E., & Frischknecht, Rolf; Stolz, Philippe; Krebs, Luana; de Wild-Scholten, Mariska; Sinha, P. (2021). Life Cycle Inventories and Life Cycle Assessments of Photovoltaic Systems 2020 Task 12 PV Sustainability. Progress in Photovoltaics: Research and Applications, 29(10), 1068–1077. www.iea-pvps.org
A7: type | B7: process
A8: unit | B8: kilowatt hour
A9: Exchanges
A10: name | B10: amount | C10: location | D10: unit | E10: categories | F10: type | G10: uncertainty type | H10: reference product | I10: comment | J10: production volume | K10: scope | L10: scope share | M10: tech share | N10: installation | O10: productivity | P10: kWp | Q10: lifetime | R10: lifetime production | S10: inverted lifetime production
A11: Energy, solar, converted | B11: 3.8503 | D11: megajoule | E11: natural resource::in air | F11: biosphere | G11: 0 | I11: (2,2,1,1,1,3); Energy loss in the system
A12: Heat, waste | B12: 0.25027 | D12: megajoule | E12: air | F12: biosphere | G12: 0 | I12: (1,na,na,na,na,na); Calculation with average annual output and share of technologies; Average degradation of 10.5% included
A13: electricity production, photovoltaic, residential | B13: 1 | C13: NA | D13: kilowatt hour | E13: photovoltaic::power plants | F13: production | G13: 0 | H13: electricity, low voltage | J13: =VLOOKUP(C13,'extension - production vol'!$B$6:$D$235,3,0) -> 13.901
A14: photovoltaic slanted-roof installation, 3 kWp, CIS, laminated, integrated, on roof | B14: =M14*S14 -> 3.057995e-08 | C14: CH | D14: unit | F14: technosphere | G14: 0 | H14: photovoltaic slanted-roof installation, 3 kWp, CIS, laminated, integrated, on roof | I14: (2,2,1,1,1,3); Calculation with average annual yield and share of technologies. Lifetime: 30a. | K14: residential | L14: =IF(K14="residential",VLOOKUP(B3,parameters!$C$41:$AG$178,18,0),IF(K14="commercial",1-VLOOKUP(B3,parameters!$C$41:$AG$178,18,0),1)) -> 0.17766752 | M14: =INDEX(parameters!$D$41:$AG$178,MATCH('PV (extension)'!B3,parameters!$C$41:$C$178,0),MATCH('PV (extension)'!A14,parameters!$D$5:$AG$5,0))/L14 -> 0.0051198231 | N14: roof-top | O14: =INDEX(parameters!$C$196:$EJ$198,MATCH('PV (extension)'!N14,parameters!$B$196:$B$198,0),MATCH('PV (extension)'!B3,parameters!$C$195:$EJ$195,0)) -> 1860.2687 | P14: 3 | Q14: 30 | R14: =Q14*P14*O14 -> 167424.18 | S14: =1/R14 -> 5.9728528e-06
A15: photovoltaic slanted-roof installation, 3 kWp, CdTe, panel, mounted, on roof | B15: =M15*S15 -> 1.9945179e-07 | C15: CH | D15: unit | F15: technosphere | G15: 0 | H15: photovoltaic slanted-roof installation, 3 kWp, CdTe, panel, mounted, on roof | I15: (2,2,1,1,1,3); Calculation with average annual yield and share of technologies. Lifetime: 30a. | K15: residential | L15: =L14 -> 0.17766752 | M15: =INDEX(parameters!$D$41:$AG$178,MATCH('PV (extension)'!B3,parameters!$C$41:$C$178,0),MATCH('PV (extension)'!A15,parameters!$D$5:$AG$5,0))/L15 -> 0.033393054 | N15: roof-top | O15: =INDEX(parameters!$C$196:$EJ$198,MATCH('PV (extension)'!N15,parameters!$B$196:$B$198,0),MATCH('PV (extension)'!B3,parameters!$C$195:$EJ$195,0)) -> 1860.2687 | P15: 3 | Q15: 30 | R15: =Q15*P15*O15 -> 167424.18 | S15: =1/R15 -> 5.9728528e-06
A16: photovoltaic slanted-roof installation, 3 kWp, micro-Si, laminated, integrated, on roof | B16: =M16*S16 -> 3.0905029e-09 | C16: RER | D16: unit | F16: technosphere | G16: 0 | H16: photovoltaic slanted-roof installation, 3 kWp, micro-Si, laminated, integrated, on roof | I16: (2,2,1,1,1,3); Calculation with average annual yield and share of technologies. Lifetime: 30a. | K16: residential | L16: =L15 -> 0.17766752 | M16: =INDEX(parameters!$D$41:$AG$178,MATCH('PV (extension)'!B3,parameters!$C$41:$C$178,0),MATCH('PV (extension)'!A16,parameters!$D$5:$AG$5,0))/L16 -> 0.00051742493 | N16: roof-top | O16: =INDEX(parameters!$C$196:$EJ$198,MATCH('PV (extension)'!N16,parameters!$B$196:$B$198,0),MATCH('PV (extension)'!B3,parameters!$C$195:$EJ$195,0)) -> 1860.2687 | P16: 3 | Q16: 30 | R16: =Q16*P16*O16 -> 167424.18 | S16: =1/R16 -> 5.9728528e-06
A17: photovoltaic slanted-roof installation, 3 kWp, micro-Si, panel, mounted, on roof | B17: =M17*S17 -> 5.3727857e-08 | C17: RER | D17: unit | F17: technosphere | G17: 0 | H17: photovoltaic slanted-roof installation, 3 kWp, micro-Si, panel, mounted, on roof | I17: (2,2,1,1,1,3); Calculation with average annual yield and share of technologies. Lifetime: 30a. | K17: residential | L17: =L16 -> 0.17766752 | M17: =INDEX(parameters!$D$41:$AG$178,MATCH('PV (extension)'!B3,parameters!$C$41:$C$178,0),MATCH('PV (extension)'!A17,parameters!$D$5:$AG$5,0))/L17 -> 0.0089953426 | N17: roof-top | O17: =INDEX(parameters!$C$196:$EJ$198,MATCH('PV (extension)'!N17,parameters!$B$196:$B$198,0),MATCH('PV (extension)'!B3,parameters!$C$195:$EJ$195,0)) -> 1860.2687 | P17: 3 | Q17: 30 | R17: =Q17*P17*O17 -> 167424.18 | S17: =1/R17 -> 5.9728528e-06
A18: photovoltaic facade installation, 3kWp, multi-Si, laminated, integrated, at building | B18: =M18*S18 -> 1.5735721e-07 | C18: RER | D18: unit | F18: technosphere | G18: 0 | H18: photovoltaic facade installation, 3kWp, multi-Si, laminated, integrated, at building | I18: (2,2,1,1,1,3); Calculation with average annual yield and share of technologies. Lifetime: 30a. | K18: residential | L18: =L17 -> 0.17766752 | M18: =INDEX(parameters!$D$41:$AG$178,MATCH('PV (extension)'!B3,parameters!$C$41:$C$178,0),MATCH('PV (extension)'!A18,parameters!$D$5:$AG$5,0))/L18 -> 0.018497835 | N18: façade | O18: =INDEX(parameters!$C$196:$EJ$198,MATCH('PV (extension)'!N18,parameters!$B$196:$B$198,0),MATCH('PV (extension)'!B3,parameters!$C$195:$EJ$195,0)) -> 1306.1461 | P18: 3 | Q18: 30 | R18: =Q18*P18*O18 -> 117553.15 | S18: =1/R18 -> 8.5067903e-06
A19: photovoltaic facade installation, 3kWp, multi-Si, panel, mounted, at building | B19: =M19*S19 -> 1.5432577e-07 | C19: RER | D19: unit | F19: technosphere | G19: 0 | H19: photovoltaic facade installation, 3kWp, multi-Si, panel, mounted, at building | I19: (2,2,1,1,1,3); Calculation with average annual yield and share of technologies. Lifetime: 30a. | K19: residential | L19: =L18 -> 0.17766752 | M19: =INDEX(parameters!$D$41:$AG$178,MATCH('PV (extension)'!B3,parameters!$C$41:$C$178,0),MATCH('PV (extension)'!A19,parameters!$D$5:$AG$5,0))/L19 -> 0.018141481 | N19: façade | O19: =INDEX(parameters!$C$196:$EJ$198,MATCH('PV (extension)'!N19,parameters!$B$196:$B$198,0),MATCH('PV (extension)'!B3,parameters!$C$195:$EJ$195,0)) -> 1306.1461 | P19: 3 | Q19: 30 | R19: =Q19*P19*O19 -> 117553.15 | S19: =1/R19 -> 8.5067903e-06
A20: photovoltaic facade installation, 3kWp, single-Si, laminated, integrated, at building | B20: =M20*S20 -> 8.2956962e-08 | C20: RER | D20: unit | F20: technosphere | G20: 0 | H20: photovoltaic facade installation, 3kWp, single-Si, laminated, integrated, at building | I20: (2,2,1,1,1,3); Calculation with average annual yield and share of technologies. Lifetime: 30a. | K20: residential | L20: =L19 -> 0.17766752 | M20: =INDEX(parameters!$D$41:$AG$178,MATCH('PV (extension)'!B3,parameters!$C$41:$C$178,0),MATCH('PV (extension)'!A20,parameters!$D$5:$AG$5,0))/L20 -> 0.0097518522 | N20: façade | O20: =INDEX(parameters!$C$196:$EJ$198,MATCH('PV (extension)'!N20,parameters!$B$196:$B$198,0),MATCH('PV (extension)'!B3,parameters!$C$195:$EJ$195,0)) -> 1306.1461 | P20: 3 | Q20: 30 | R20: =Q20*P20*O20 -> 117553.15 | S20: =1/R20 -> 8.5067903e-06
A21: photovoltaic facade installation, 3kWp, single-Si, panel, mounted, at building | B21: =M21*S21 -> 8.2885184e-08 | C21: RER | D21: unit | F21: technosphere | G21: 0 | H21: photovoltaic facade installation, 3kWp, single-Si, panel, mounted, at building | I21: (2,2,1,1,1,3); Calculation with average annual yield and share of technologies. Lifetime: 30a. | K21: residential | L21: =L20 -> 0.17766752 | M21: =INDEX(parameters!$D$41:$AG$178,MATCH('PV (extension)'!B3,parameters!$C$41:$C$178,0),MATCH('PV (extension)'!A21,parameters!$D$5:$AG$5,0))/L21 -> 0.0097434145 | N21: façade | O21: =INDEX(parameters!$C$196:$EJ$198,MATCH('PV (extension)'!N21,parameters!$B$196:$B$198,0),MATCH('PV (extension)'!B3,parameters!$C$195:$EJ$195,0)) -> 1306.1461 | P21: 3 | Q21: 30 | R21: =Q21*P21*O21 -> 117553.15 | S21: =1/R21 -> 8.5067903e-06
A22: photovoltaic flat-roof installation, 3kWp, multi-Si, on roof | B22: =M22*S22 -> 1.7019211e-06 | C22: RER | D22: unit | F22: technosphere | G22: 0 | H22: photovoltaic flat-roof installation, 3kWp, multi-Si, on roof | I22: (2,2,1,1,1,3); Calculation with average annual yield and share of technologies. Lifetime: 30a. | K22: residential | L22: =L21 -> 0.17766752 | M22: =INDEX(parameters!$D$41:$AG$178,MATCH('PV (extension)'!B3,parameters!$C$41:$C$178,0),MATCH('PV (extension)'!A22,parameters!$D$5:$AG$5,0))/L22 -> 0.28494275 | N22: roof-top | O22: =INDEX(parameters!$C$196:$EJ$198,MATCH('PV (extension)'!N22,parameters!$B$196:$B$198,0),MATCH('PV (extension)'!B3,parameters!$C$195:$EJ$195,0)) -> 1860.2687 | P22: 3 | Q22: 30 | R22: =Q22*P22*O22 -> 167424.18 | S22: =1/R22 -> 5.9728528e-06
A23: photovoltaic flat-roof installation, 3kWp, single-Si, on roof | B23: =M23*S23 -> 8.8837815e-07 | C23: RER | D23: unit | F23: technosphere | G23: 0 | H23: photovoltaic flat-roof installation, 3kWp, single-Si, on roof | I23: (2,2,1,1,1,3); Calculation with average annual yield and share of technologies. Lifetime: 30a. | K23: residential | L23: =L22 -> 0.17766752 | M23: =INDEX(parameters!$D$41:$AG$178,MATCH('PV (extension)'!B3,parameters!$C$41:$C$178,0),MATCH('PV (extension)'!A23,parameters!$D$5:$AG$5,0))/L23 -> 0.14873599 | N23: roof-top | O23: =INDEX(parameters!$C$196:$EJ$198,MATCH('PV (extension)'!N23,parameters!$B$196:$B$198,0),MATCH('PV (extension)'!B3,parameters!$C$195:$EJ$195,0)) -> 1860.2687 | P23: 3 | Q23: 30 | R23: =Q23*P23*O23 -> 167424.18 | S23: =1/R23 -> 5.9728528e-06
A24: photovoltaic slanted-roof installation, 3kWp, CIS, panel, mounted, on roof | B24: =M24*S24 -> 4.9137815e-07 | C24: CH | D24: unit | F24: technosphere | G24: 0 | H24: photovoltaic slanted-roof installation, 3kWp, CIS, panel, mounted, on roof | I24: (2,2,1,1,1,3); Calculation with average annual yield and share of technologies. Lifetime: 30a. | K24: residential | L24: =L23 -> 0.17766752 | M24: =INDEX(parameters!$D$41:$AG$178,MATCH('PV (extension)'!B3,parameters!$C$41:$C$178,0),MATCH('PV (extension)'!A24,parameters!$D$5:$AG$5,0))/L24 -> 0.082268586 | N24: roof-top | O24: =INDEX(parameters!$C$196:$EJ$198,MATCH('PV (extension)'!N24,parameters!$B$196:$B$198,0),MATCH('PV (extension)'!B3,parameters!$C$195:$EJ$195,0)) -> 1860.2687 | P24: 3 | Q24: 30 | R24: =Q24*P24*O24 -> 167424.18 | S24: =1/R24 -> 5.9728528e-06
A25: photovoltaic slanted-roof installation, 3kWp, CdTe, laminated, integrated, on roof | B25: =M25*S25 -> 1.3758896e-08 | C25: CH | D25: unit | F25: technosphere | G25: 0 | H25: photovoltaic slanted-roof installation, 3kWp, CdTe, laminated, integrated, on roof | I25: (2,2,1,1,1,3); Calculation with average annual yield and share of technologies. Lifetime: 30a. | K25: residential | L25: =L24 -> 0.17766752 | M25: =INDEX(parameters!$D$41:$AG$178,MATCH('PV (extension)'!B3,parameters!$C$41:$C$178,0),MATCH('PV (extension)'!A25,parameters!$D$5:$AG$5,0))/L25 -> 0.002303572 | N25: roof-top | O25: =INDEX(parameters!$C$196:$EJ$198,MATCH('PV (extension)'!N25,parameters!$B$196:$B$198,0),MATCH('PV (extension)'!B3,parameters!$C$195:$EJ$195,0)) -> 1860.2687 | P25: 3 | Q25: 30 | R25: =Q25*P25*O25 -> 167424.18 | S25: =1/R25 -> 5.9728528e-06
A26: photovoltaic slanted-roof installation, 3kWp, multi-Si, laminated, integrated, on roof | B26: =M26*S26 -> 8.1742412e-08 | C26: RER | D26: unit | F26: technosphere | G26: 0 | H26: photovoltaic slanted-roof installation, 3kWp, multi-Si, laminated, integrated, on roof | I26: (2,2,1,1,1,3); Calculation with average annual yield and share of technologies. Lifetime: 30a. | K26: residential | L26: =L25 -> 0.17766752 | M26: =INDEX(parameters!$D$41:$AG$178,MATCH('PV (extension)'!B3,parameters!$C$41:$C$178,0),MATCH('PV (extension)'!A26,parameters!$D$5:$AG$5,0))/L26 -> 0.013685656 | N26: roof-top | O26: =INDEX(parameters!$C$196:$EJ$198,MATCH('PV (extension)'!N26,parameters!$B$196:$B$198,0),MATCH('PV (extension)'!B3,parameters!$C$195:$EJ$195,0)) -> 1860.2687 | P26: 3 | Q26: 30 | R26: =Q26*P26*O26 -> 167424.18 | S26: =1/R26 -> 5.9728528e-06
A27: photovoltaic slanted-roof installation, 3kWp, multi-Si, panel, mounted, on roof | B27: =M27*S27 -> 1.3991397e-06 | C27: RER | D27: unit | F27: technosphere | G27: 0 | H27: photovoltaic slanted-roof installation, 3kWp, multi-Si, panel, mounted, on roof | I27: (2,2,1,1,1,3); Calculation with average annual yield and share of technologies. Lifetime: 30a. | K27: residential | L27: =L26 -> 0.17766752 | M27: =INDEX(parameters!$D$41:$AG$178,MATCH('PV (extension)'!B3,parameters!$C$41:$C$178,0),MATCH('PV (extension)'!A27,parameters!$D$5:$AG$5,0))/L27 -> 0.23424983 | N27: roof-top | O27: =INDEX(parameters!$C$196:$EJ$198,MATCH('PV (extension)'!N27,parameters!$B$196:$B$198,0),MATCH('PV (extension)'!B3,parameters!$C$195:$EJ$195,0)) -> 1860.2687 | P27: 3 | Q27: 30 | R27: =Q27*P27*O27 -> 167424.18 | S27: =1/R27 -> 5.9728528e-06
A28: photovoltaic slanted-roof installation, 3kWp, single-Si, laminated, integrated, on roof | B28: =M28*S28 -> 4.3200561e-08 | C28: RER | D28: unit | F28: technosphere | G28: 0 | H28: photovoltaic slanted-roof installation, 3kWp, single-Si, laminated, integrated, on roof | I28: (2,2,1,1,1,3); Calculation with average annual yield and share of technologies. Lifetime: 30a. | K28: residential | L28: =L27 -> 0.17766752 | M28: =INDEX(parameters!$D$41:$AG$178,MATCH('PV (extension)'!B3,parameters!$C$41:$C$178,0),MATCH('PV (extension)'!A28,parameters!$D$5:$AG$5,0))/L28 -> 0.0072328187 | N28: roof-top | O28: =INDEX(parameters!$C$196:$EJ$198,MATCH('PV (extension)'!N28,parameters!$B$196:$B$198,0),MATCH('PV (extension)'!B3,parameters!$C$195:$EJ$195,0)) -> 1860.2687 | P28: 3 | Q28: 30 | R28: =Q28*P28*O28 -> 167424.18 | S28: =1/R28 -> 5.9728528e-06
A29: photovoltaic slanted-roof installation, 3kWp, single-Si, panel, mounted, on roof | B29: =M29*S29 -> 7.312001e-07 | C29: RER | D29: unit | F29: technosphere | G29: 0 | H29: photovoltaic slanted-roof installation, 3kWp, single-Si, panel, mounted, on roof | I29: (2,2,1,1,1,3); Calculation with average annual yield and share of technologies. Lifetime: 30a. | K29: residential | L29: =L28 -> 0.17766752 | M29: =INDEX(parameters!$D$41:$AG$178,MATCH('PV (extension)'!B3,parameters!$C$41:$C$178,0),MATCH('PV (extension)'!A29,parameters!$D$5:$AG$5,0))/L29 -> 0.12242058 | N29: roof-top | O29: =INDEX(parameters!$C$196:$EJ$198,MATCH('PV (extension)'!N29,parameters!$B$196:$B$198,0),MATCH('PV (extension)'!B3,parameters!$C$195:$EJ$195,0)) -> 1860.2687 | P29: 3 | Q29: 30 | R29: =Q29*P29*O29 -> 167424.18 | S29: =1/R29 -> 5.9728528e-06
A30: market for tap water | B30: 0.0037026 | C30: Europe without Switzerland | D30: kilogram | F30: technosphere | G30: 0 | H30: tap water | I30: (2,2,1,1,1,3); Estimation 20l/m2 panel
A31: treatment of wastewater, from residence, capacity 1.1E10l/year | B31: -3.3323e-06 | C31: CH | D31: cubic meter | F31: technosphere | G31: 0 | H31: wastewater, from residence | I31: (2,2,1,1,1,3); Estimation 20l/m2 panel
A33: Activity | B33: electricity production, photovoltaic, commercial
A34: comment | B34: =_xlfn._LONGTEXT("Dataset created adapted from the methodology followed by: Life Cycle Inventories and Life Cycle Assessments of Photovoltaic Systems 2020 Task 12 PV Sustainability, December 2020, DOI: 10.13140/RG.2.2.17977.19041 However, the technology split is not countr","y-specific but based based on weighted average of OECD countries. Production volume provided by IRENA 2025: https://www.irena.org/Publications/2025/Jul/Renewable-energy-statistics-2025 Open-ground PV panel productivity in the country based on area-weighte","d estimate from the Global Solar Atlas: https://globalsolaratlas.info/download/world The lifetime of PV systems is estimated at 30 years based on the PEFCR PV electricity. Production mix of photovoltaic electricity in the country. Annual output, Roof-Top",": ")&HLOOKUP(B35,parameters!$C$195:$EJ$198,2,0)&" kWh/kWp. Annual output, Facade: "&HLOOKUP(B35,parameters!$C$195:$EJ$198,3,0)&" kWh/kWp. Annual output, Open-ground: "&HLOOKUP(B35,parameters!$C$195:$EJ$198,4,0)&_xlfn._LONGTEXT(" kWh/kWp. Amount of solar energy transformed to electricity. Waste heat emission due to losses of electricity in the system. Technology: Electricity production with grid-connected photovoltaic power plants. Time period: Time of publications Production v","olume: ")&VLOOKUP(B35,'extension - production vol'!$B$6:$D$235,3,0)&_xlfn._LONGTEXT(" GWh in 2025. Sampling: Statistical data and model calculations Extrapolations: Use of PV technology data investigated for other countries (Switzerland). Correction of average yield with Swiss data. Uncertainty: None Author: Romain Sacchi, PSI, romain.","sacchi@psi.ch") -> Dataset created adapted from the methodology followed by: Life Cycle Inventories and Life Cycle Assessments of Photovoltaic Systems 2020 Task 12 PV Sustainability, December 2020, DOI: 10.13140/RG.2.2.17977.19041 However, the technology split is not country-specific but based based on weighted average of OECD countries. Production volume provided by IRENA 2025: https://www.irena.org/Publications/2025/Jul/Renewable-energy-statistics-2025 Open-ground PV panel productivity in the country based on area-weighted estimate from the Global Solar Atlas: https://globalsolaratlas.info/download/world The lifetime of PV systems is estimated at 30 years based on the PEFCR PV electricity. Production mix of photovoltaic electricity in the country. Annual output, Roof-Top: 1860.26870229946 kWh/kWp. Annual output, Facade: 1306.14611012515 kWh/kWp. Annual output, Open-ground: 1979.00925776538 kWh/kWp. Amount of solar energy transformed to electricity. Waste heat emission due to losses of electricity in the system. Technology: Electricity production with grid-connected photovoltaic power plants. Time period: Time of publications Production volume: 13.901 GWh in 2025. Sampling: Statistical data and model calculations Extrapolations: Use of PV technology data investigated for other countries (Switzerland). Correction of average yield with Swiss data. Uncertainty: None Author: Romain Sacchi, PSI, romain.sacchi@psi.ch
A35: location | B35: NA
A36: production amount | B36: 1
A37: reference product | B37: electricity, low voltage
A38: source | B38: Fthenakis, V., Leccisi, E., & Frischknecht, Rolf; Stolz, Philippe; Krebs, Luana; de Wild-Scholten, Mariska; Sinha, P. (2021). Life Cycle Inventories and Life Cycle Assessments of Photovoltaic Systems 2020 Task 12 PV Sustainability. Progress in Photovoltaics: Research and Applications, 29(10), 1068–1077. www.iea-pvps.org
A39: type | B39: process
A40: unit | B40: kilowatt hour
A41: Exchanges
A42: name | B42: amount | C42: location | D42: unit | E42: categories | F42: type | G42: uncertainty type | H42: reference product | I42: comment | J42: production volume | K42: scope | L42: scope share | M42: tech share | N42: installation | O42: productivity | P42: kWp | Q42: lifetime | R42: lifetime production | S42: inverted lifetime production
A43: Energy, solar, converted | B43: 3.8503 | D43: megajoule | E43: natural resource::in air | F43: biosphere | G43: 0 | I43: (2,2,1,1,1,3); Energy loss in the system
A44: Heat, waste | B44: 0.25027 | D44: megajoule | E44: air | F44: biosphere | G44: 0 | I44: (1,na,na,na,na,na); Calculation with average annual output and share of technologies; Average degradation of 10.5% included
A45: electricity production, photovoltaic, commercial | B45: 1 | C45: NA | D45: kilowatt hour | E45: photovoltaic::power plants | F45: production | G45: 0 | H45: electricity, low voltage | J45: =VLOOKUP(C45,'extension - production vol'!$B$6:$D$235,3,0) -> 13.901
A46: photovoltaic flat-roof installation, 156 kWp, multi-Si, on roof | B46: =M46*S46 -> 1.410257e-08 | C46: CH | D46: unit | F46: technosphere | G46: 0 | H46: photovoltaic flat-roof installation, 156 kWp, multi-Si, on roof | I46: (2,2,1,1,1,3); Calculation with average annual yield and share of technologies. Lifetime: 30a. | K46: commercial | L46: =IF(K46="residential",VLOOKUP(B35,parameters!$C$41:$AG$178,18,0),IF(K46="commercial",1-VLOOKUP(B35,parameters!$C$41:$AG$178,18,0),1)) -> 0.82233248 | M46: =INDEX(parameters!$D$41:$AG$178,MATCH('PV (extension)'!B35,parameters!$C$41:$C$178,0),MATCH('PV (extension)'!A46,parameters!$D$5:$AG$5,0))/L46 -> 0.12277779 | N46: roof-top | O46: =INDEX(parameters!$C$196:$EJ$198,MATCH('PV (extension)'!N46,parameters!$B$196:$B$198,0),MATCH('PV (extension)'!B35,parameters!$C$195:$EJ$195,0)) -> 1860.2687 | P46: 156 | Q46: 30 | R46: =Q46*P46*O46 -> 8706057.5 | S46: =1/R46 -> 1.1486255e-07
A47: photovoltaic flat-roof installation, 156 kWp, single-Si, on roof | B47: =M47*S47 -> 7.3666715e-09 | C47: CH | D47: unit | F47: technosphere | G47: 0 | H47: photovoltaic flat-roof installation, 156 kWp, single-Si, on roof | I47: (2,2,1,1,1,3); Calculation with average annual yield and share of technologies. Lifetime: 30a. | K47: commercial | L47: =L46 -> 0.82233248 | M47: =INDEX(parameters!$D$41:$AG$178,MATCH('PV (extension)'!B35,parameters!$C$41:$C$178,0),MATCH('PV (extension)'!A47,parameters!$D$5:$AG$5,0))/L47 -> 0.064134666 | N47: roof-top | O47: =INDEX(parameters!$C$196:$EJ$198,MATCH('PV (extension)'!N47,parameters!$B$196:$B$198,0),MATCH('PV (extension)'!B35,parameters!$C$195:$EJ$195,0)) -> 1860.2687 | P47: 156 | Q47: 30 | R47: =Q47*P47*O47 -> 8706057.5 | S47: =1/R47 -> 1.1486255e-07
A48: photovoltaic open ground installation, 570 kWp, CIS, on open ground | B48: =M48*S48 -> 3.6308636e-10 | C48: RER | D48: unit | F48: technosphere | G48: 0 | H48: photovoltaic open ground installation, 570 kWp, CIS, on open ground | I48: (2,2,1,1,1,3); Calculation with average annual yield and share of technologies. Lifetime: 30a. | K48: commercial | L48: =L47 -> 0.82233248 | M48: =INDEX(parameters!$D$41:$AG$178,MATCH('PV (extension)'!B35,parameters!$C$41:$C$178,0),MATCH('PV (extension)'!A48,parameters!$D$5:$AG$5,0))/L48 -> 0.012287227 | N48: central | O48: =INDEX(parameters!$C$196:$EJ$198,MATCH('PV (extension)'!N48,parameters!$B$196:$B$198,0),MATCH('PV (extension)'!B35,parameters!$C$195:$EJ$195,0)) -> 1979.0093 | P48: 570 | Q48: 30 | R48: =Q48*P48*O48 -> 33841058 | S48: =1/R48 -> 2.9549903e-08
A49: photovoltaic open ground installation, 570 kWp, CdTe, on open ground | B49: =M49*S49 -> 2.6672044e-09 | C49: RER | D49: unit | F49: technosphere | G49: 0 | H49: photovoltaic open ground installation, 570 kWp, CdTe, on open ground | I49: (2,2,1,1,1,3); Calculation with average annual yield and share of technologies. Lifetime: 30a. | K49: commercial | L49: =L48 -> 0.82233248 | M49: =INDEX(parameters!$D$41:$AG$178,MATCH('PV (extension)'!B35,parameters!$C$41:$C$178,0),MATCH('PV (extension)'!A49,parameters!$D$5:$AG$5,0))/L49 -> 0.090261021 | N49: central | O49: =INDEX(parameters!$C$196:$EJ$198,MATCH('PV (extension)'!N49,parameters!$B$196:$B$198,0),MATCH('PV (extension)'!B35,parameters!$C$195:$EJ$195,0)) -> 1979.0093 | P49: 570 | Q49: 30 | R49: =Q49*P49*O49 -> 33841058 | S49: =1/R49 -> 2.9549903e-08
A50: photovoltaic open ground installation, 570 kWp, micro-Si, on open ground | B50: =M50*S50 -> 2.8270474e-11 | C50: RER | D50: unit | F50: technosphere | G50: 0 | H50: photovoltaic open ground installation, 570 kWp, micro-Si, on open ground | I50: (2,2,1,1,1,3); Calculation with average annual yield and share of technologies. Lifetime: 30a. | K50: commercial | L50: =L49 -> 0.82233248 | M50: =INDEX(parameters!$D$41:$AG$178,MATCH('PV (extension)'!B35,parameters!$C$41:$C$178,0),MATCH('PV (extension)'!A50,parameters!$D$5:$AG$5,0))/L50 -> 0.00095670277 | N50: central | O50: =INDEX(parameters!$C$196:$EJ$198,MATCH('PV (extension)'!N50,parameters!$B$196:$B$198,0),MATCH('PV (extension)'!B35,parameters!$C$195:$EJ$195,0)) -> 1979.0093 | P50: 570 | Q50: 30 | R50: =Q50*P50*O50 -> 33841058 | S50: =1/R50 -> 2.9549903e-08
A51: photovoltaic open ground installation, 570 kWp, multi-Si, on open ground | B51: =M51*S51 -> 9.4606917e-09 | C51: RER | D51: unit | F51: technosphere | G51: 0 | H51: photovoltaic open ground installation, 570 kWp, multi-Si, on open ground | I51: (2,2,1,1,1,3); Calculation with average annual yield and share of technologies. Lifetime: 30a. | K51: commercial | L51: =L50 -> 0.82233248 | M51: =INDEX(parameters!$D$41:$AG$178,MATCH('PV (extension)'!B35,parameters!$C$41:$C$178,0),MATCH('PV (extension)'!A51,parameters!$D$5:$AG$5,0))/L51 -> 0.32015982 | N51: central | O51: =INDEX(parameters!$C$196:$EJ$198,MATCH('PV (extension)'!N51,parameters!$B$196:$B$198,0),MATCH('PV (extension)'!B35,parameters!$C$195:$EJ$195,0)) -> 1979.0093 | P51: 570 | Q51: 30 | R51: =Q51*P51*O51 -> 33841058 | S51: =1/R51 -> 2.9549903e-08
A52: photovoltaic open ground installation, 570 kWp, single-Si, on open ground | B52: =M52*S52 -> 5.0183582e-09 | C52: RER | D52: unit | F52: technosphere | G52: 0 | H52: photovoltaic open ground installation, 570 kWp, single-Si, on open ground | I52: (2,2,1,1,1,3); Calculation with average annual yield and share of technologies. Lifetime: 30a. | K52: commercial | L52: =L51 -> 0.82233248 | M52: =INDEX(parameters!$D$41:$AG$178,MATCH('PV (extension)'!B35,parameters!$C$41:$C$178,0),MATCH('PV (extension)'!A52,parameters!$D$5:$AG$5,0))/L52 -> 0.16982655 | N52: central | O52: =INDEX(parameters!$C$196:$EJ$198,MATCH('PV (extension)'!N52,parameters!$B$196:$B$198,0),MATCH('PV (extension)'!B35,parameters!$C$195:$EJ$195,0)) -> 1979.0093 | P52: 570 | Q52: 30 | R52: =Q52*P52*O52 -> 33841058 | S52: =1/R52 -> 2.9549903e-08
A53: photovoltaic slanted-roof installation, 93 kWp, multi-Si, laminated, integrated, on roof | B53: =M53*S53 -> 1.5485977e-09 | C53: CH | D53: unit | F53: technosphere | G53: 0 | H53: photovoltaic slanted-roof installation, 93 kWp, multi-Si, laminated, integrated, on roof | I53: (2,2,1,1,1,3); Calculation with average annual yield and share of technologies. Lifetime: 30a. | K53: commercial | L53: =L52 -> 0.82233248 | M53: =INDEX(parameters!$D$41:$AG$178,MATCH('PV (extension)'!B35,parameters!$C$41:$C$178,0),MATCH('PV (extension)'!A53,parameters!$D$5:$AG$5,0))/L53 -> 0.008037454 | N53: roof-top | O53: =INDEX(parameters!$C$196:$EJ$198,MATCH('PV (extension)'!N53,parameters!$B$196:$B$198,0),MATCH('PV (extension)'!B35,parameters!$C$195:$EJ$195,0)) -> 1860.2687 | P53: 93 | Q53: 30 | R53: =Q53*P53*O53 -> 5190149.7 | S53: =1/R53 -> 1.9267267e-07
A54: photovoltaic slanted-roof installation, 93 kWp, multi-Si, panel, mounted, on roof | B54: =M54*S54 -> 2.6258725e-08 | C54: CH | D54: unit | F54: technosphere | G54: 0 | H54: photovoltaic slanted-roof installation, 93 kWp, multi-Si, panel, mounted, on roof | I54: (2,2,1,1,1,3); Calculation with average annual yield and share of technologies. Lifetime: 30a. | K54: commercial | L54: =L53 -> 0.82233248 | M54: =INDEX(parameters!$D$41:$AG$178,MATCH('PV (extension)'!B35,parameters!$C$41:$C$178,0),MATCH('PV (extension)'!A54,parameters!$D$5:$AG$5,0))/L54 -> 0.13628671 | N54: roof-top | O54: =INDEX(parameters!$C$196:$EJ$198,MATCH('PV (extension)'!N54,parameters!$B$196:$B$198,0),MATCH('PV (extension)'!B35,parameters!$C$195:$EJ$195,0)) -> 1860.2687 | P54: 93 | Q54: 30 | R54: =Q54*P54*O54 -> 5190149.7 | S54: =1/R54 -> 1.9267267e-07
A55: photovoltaic slanted-roof installation, 93 kWp, single-Si, laminated, integrated, on roof | B55: =M55*S55 -> 8.1865584e-10 | C55: CH | D55: unit | F55: technosphere | G55: 0 | H55: photovoltaic slanted-roof installation, 93 kWp, single-Si, laminated, integrated, on roof | I55: (2,2,1,1,1,3); Calculation with average annual yield and share of technologies. Lifetime: 30a. | K55: commercial | L55: =L54 -> 0.82233248 | M55: =INDEX(parameters!$D$41:$AG$178,MATCH('PV (extension)'!B35,parameters!$C$41:$C$178,0),MATCH('PV (extension)'!A55,parameters!$D$5:$AG$5,0))/L55 -> 0.0042489464 | N55: roof-top | O55: =INDEX(parameters!$C$196:$EJ$198,MATCH('PV (extension)'!N55,parameters!$B$196:$B$198,0),MATCH('PV (extension)'!B35,parameters!$C$195:$EJ$195,0)) -> 1860.2687 | P55: 93 | Q55: 30 | R55: =Q55*P55*O55 -> 5190149.7 | S55: =1/R55 -> 1.9267267e-07
A56: photovoltaic slanted-roof installation, 93 kWp, single-Si, panel, mounted, on roof | B56: =M56*S56 -> 1.3754596e-08 | C56: CH | D56: unit | F56: technosphere | G56: 0 | H56: photovoltaic slanted-roof installation, 93 kWp, single-Si, panel, mounted, on roof | I56: (2,2,1,1,1,3); Calculation with average annual yield and share of technologies. Lifetime: 30a. | K56: commercial | L56: =L55 -> 0.82233248 | M56: =INDEX(parameters!$D$41:$AG$178,MATCH('PV (extension)'!B35,parameters!$C$41:$C$178,0),MATCH('PV (extension)'!A56,parameters!$D$5:$AG$5,0))/L56 -> 0.071388412 | N56: roof-top | O56: =INDEX(parameters!$C$196:$EJ$198,MATCH('PV (extension)'!N56,parameters!$B$196:$B$198,0),MATCH('PV (extension)'!B35,parameters!$C$195:$EJ$195,0)) -> 1860.2687 | P56: 93 | Q56: 30 | R56: =Q56*P56*O56 -> 5190149.7 | S56: =1/R56 -> 1.9267267e-07
A57: market for tap water | B57: 0.0037026 | C57: Europe without Switzerland | D57: kilogram | F57: technosphere | G57: 0 | H57: tap water | I57: (2,2,1,1,1,3); Estimation 20l/m2 panel
A58: treatment of wastewater, from residence, capacity 1.1E10l/year | B58: -3.3323e-06 | C58: CH | D58: cubic meter | F58: technosphere | G58: 0 | H58: wastewater, from residence | I58: (2,2,1,1,1,3); Estimation 20l/m2 panel
A60: Activity | B60: electricity production, photovoltaic
A61: comment | B61: =_xlfn._LONGTEXT("Dataset created adapted from the methodology followed by: Life Cycle Inventories and Life Cycle Assessments of Photovoltaic Systems 2020 Task 12 PV Sustainability, December 2020, DOI: 10.13140/RG.2.2.17977.19041 However, the technology split is not countr","y-specific but based based on weighted average of OECD countries. Production volume provided by IRENA 2025: https://www.irena.org/Publications/2025/Jul/Renewable-energy-statistics-2025 Open-ground PV panel productivity in the country based on area-weighte","d estimate from the Global Solar Atlas: https://globalsolaratlas.info/download/world The lifetime of PV systems is estimated at 30 years based on the PEFCR PV electricity. Production mix of photovoltaic electricity in the country. Annual output, Roof-Top",": ")&HLOOKUP(B62,parameters!$C$195:$EJ$198,2,0)&" kWh/kWp. Annual output, Facade: "&HLOOKUP(B62,parameters!$C$195:$EJ$198,3,0)&" kWh/kWp. Annual output, Open-ground: "&HLOOKUP(B62,parameters!$C$195:$EJ$198,4,0)&_xlfn._LONGTEXT(" kWh/kWp. Amount of solar energy transformed to electricity. Waste heat emission due to losses of electricity in the system. Technology: Electricity production with grid-connected photovoltaic power plants. Time period: Time of publications Production v","olume: ")&VLOOKUP(B62,'extension - production vol'!$B$6:$D$235,3,0)&_xlfn._LONGTEXT(" GWh in 2025. Sampling: Statistical data and model calculations Extrapolations: Use of PV technology data investigated for other countries (Switzerland). Correction of average yield with Swiss data. Uncertainty: None Author: Romain Sacchi, PSI, romain.","sacchi@psi.ch") -> Dataset created adapted from the methodology followed by: Life Cycle Inventories and Life Cycle Assessments of Photovoltaic Systems 2020 Task 12 PV Sustainability, December 2020, DOI: 10.13140/RG.2.2.17977.19041 However, the technology split is not country-specific but based based on weighted average of OECD countries. Production volume provided by IRENA 2025: https://www.irena.org/Publications/2025/Jul/Renewable-energy-statistics-2025 Open-ground PV panel productivity in the country based on area-weighted estimate from the Global Solar Atlas: https://globalsolaratlas.info/download/world The lifetime of PV systems is estimated at 30 years based on the PEFCR PV electricity. Production mix of photovoltaic electricity in the country. Annual output, Roof-Top: 1860.26870229946 kWh/kWp. Annual output, Facade: 1306.14611012515 kWh/kWp. Annual output, Open-ground: 1979.00925776538 kWh/kWp. Amount of solar energy transformed to electricity. Waste heat emission due to losses of electricity in the system. Technology: Electricity production with grid-connected photovoltaic power plants. Time period: Time of publications Production volume: 13.901 GWh in 2025. Sampling: Statistical data and model calculations Extrapolations: Use of PV technology data investigated for other countries (Switzerland). Correction of average yield with Swiss data. Uncertainty: None Author: Romain Sacchi, PSI, romain.sacchi@psi.ch
A62: location | B62: NA
A63: production amount | B63: 1
A64: reference product | B64: electricity, low voltage
A65: source | B65: Fthenakis, V., Leccisi, E., & Frischknecht, Rolf; Stolz, Philippe; Krebs, Luana; de Wild-Scholten, Mariska; Sinha, P. (2021). Life Cycle Inventories and Life Cycle Assessments of Photovoltaic Systems 2020 Task 12 PV Sustainability. Progress in Photovoltaics: Research and Applications, 29(10), 1068–1077. www.iea-pvps.org
A66: type | B66: process
A67: unit | B67: kilowatt hour
A68: Exchanges
A69: name | B69: amount | C69: location | D69: unit | E69: categories | F69: type | G69: uncertainty type | H69: loc | I69: scale | J69: comment | K69: negative | L69: reference product | M69: production volume | N69: scope | O69: scope share | P69: tech share | Q69: installation | R69: productivity | S69: kWp | T69: lifetime | U69: lifetime production | V69: inverted lifetime production
A70: Energy, solar, converted | B70: 3.8503 | D70: megajoule | E70: natural resource::in air | F70: biosphere | G70: 2 | H70: 1.3481511 | I70: 0.043409846 | J70: (2,2,1,1,1,3); Energy loss in the system
A71: Heat, waste | B71: 0.25027 | D71: megajoule | E71: air | F71: biosphere | G71: 2 | H71: -1.3852149 | I71: 0.024395082 | J71: (1,na,na,na,na,na); Calculation
A72: electricity production, photovoltaic | B72: 1 | C72: NA | D72: kilowatt hour | E72: photovoltaic::power plants | F72: production | G72: 0 | H72: 1 | L72: electricity, low voltage | M72: =VLOOKUP(C72,'extension - production vol'!$B$6:$D$235,3,0) -> 13.901
A73: photovoltaic flat-roof installation, 156 kWp, multi-Si, on roof | B73: =P73*V73 -> 1.1597002e-08 | C73: CH | D73: unit | F73: technosphere | G73: 2 | H73: -18.468003 | I73: 0.097988942 | J73: (2,2,1,1,1,3); Calculation with average annual yield and share of technologies. Lifetime: 30a. | L73: photovoltaic flat-roof installation, 156 kWp, multi-Si, on roof | N73: all | O73: 1 | P73: =INDEX(parameters!$D$41:$AG$178,MATCH('PV (extension)'!B62,parameters!$C$41:$C$178,0),MATCH('PV (extension)'!A73,parameters!$D$5:$AG$5,0))/O73 -> 0.10096416 | Q73: roof-top | R73: =INDEX(parameters!$C$196:$EJ$198,MATCH('PV (extension)'!Q73,parameters!$B$196:$B$198,0),MATCH('PV (extension)'!B62,parameters!$C$195:$EJ$195,0)) -> 1860.2687 | S73: 156 | T73: 30 | U73: =T73*S73*R73 -> 8706057.5 | V73: =1/U73 -> 1.1486255e-07
A74: photovoltaic flat-roof installation, 156 kWp, single-Si, on roof | B74: =P74*V74 -> 6.0578533e-09 | C74: CH | D74: unit | F74: technosphere | G74: 2 | H74: -19.10362 | I74: 0.097988942 | J74: (2,2,1,1,1,3); Calculation with average annual yield and share of technologies. Lifetime: 30a. | L74: photovoltaic flat-roof installation, 156 kWp, single-Si, on roof | N74: all | O74: 1 | P74: =INDEX(parameters!$D$41:$AG$178,MATCH('PV (extension)'!B62,parameters!$C$41:$C$178,0),MATCH('PV (extension)'!A74,parameters!$D$5:$AG$5,0))/O74 -> 0.052740019 | Q74: roof-top | R74: =INDEX(parameters!$C$196:$EJ$198,MATCH('PV (extension)'!Q74,parameters!$B$196:$B$198,0),MATCH('PV (extension)'!B62,parameters!$C$195:$EJ$195,0)) -> 1860.2687 | S74: 156 | T74: 30 | U74: =T74*S74*R74 -> 8706057.5 | V74: =1/U74 -> 1.1486255e-07
A75: photovoltaic slanted-roof installation, 3 kWp, CIS, laminated, integrated, on roof | B75: =P75*V75 -> 5.4330637e-09 | C75: CH | D75: unit | F75: technosphere | G75: 2 | H75: -19.697439 | I75: 0.097988942 | J75: (2,2,1,1,1,3); Calculation with average annual yield and share of technologies. Lifetime: 30a. | L75: photovoltaic slanted-roof installation, 3 kWp, CIS, laminated, integrated, on roof | N75: all | O75: 1 | P75: =INDEX(parameters!$D$41:$AG$178,MATCH('PV (extension)'!B62,parameters!$C$41:$C$178,0),MATCH('PV (extension)'!A75,parameters!$D$5:$AG$5,0))/O75 -> 0.00090962625 | Q75: roof-top | R75: =INDEX(parameters!$C$196:$EJ$198,MATCH('PV (extension)'!Q75,parameters!$B$196:$B$198,0),MATCH('PV (extension)'!B62,parameters!$C$195:$EJ$195,0)) -> 1860.2687 | S75: 3 | T75: 30 | U75: =T75*S75*R75 -> 167424.18 | V75: =1/U75 -> 5.9728528e-06
A76: photovoltaic slanted-roof installation, 3 kWp, CdTe, panel, mounted, on roof | B76: =P76*V76 -> 3.5436105e-08 | C76: CH | D76: unit | F76: technosphere | G76: 2 | H76: -16.69298 | I76: 0.097988942 | J76: (2,2,1,1,1,3); Calculation with average annual yield and share of technologies. Lifetime: 30a. | L76: photovoltaic slanted-roof installation, 3 kWp, CdTe, panel, mounted, on roof | N76: all | O76: 1 | P76: =INDEX(parameters!$D$41:$AG$178,MATCH('PV (extension)'!B62,parameters!$C$41:$C$178,0),MATCH('PV (extension)'!A76,parameters!$D$5:$AG$5,0))/O76 -> 0.0059328609 | Q76: roof-top | R76: =INDEX(parameters!$C$196:$EJ$198,MATCH('PV (extension)'!Q76,parameters!$B$196:$B$198,0),MATCH('PV (extension)'!B62,parameters!$C$195:$EJ$195,0)) -> 1860.2687 | S76: 3 | T76: 30 | U76: =T76*S76*R76 -> 167424.18 | V76: =1/U76 -> 5.9728528e-06
A77: photovoltaic slanted-roof installation, 3 kWp, micro-Si, laminated, integrated, on roof | B77: =P77*V77 -> 5.4908198e-10 | C77: RER | D77: unit | F77: technosphere | G77: 2 | H77: -21.54327 | I77: 0.097988942 | J77: (2,2,1,1,1,3); Calculation with average annual yield and share of technologies. Lifetime: 30a. | L77: photovoltaic slanted-roof installation, 3 kWp, micro-Si, laminated, integrated, on roof | N77: all | O77: 1 | P77: =INDEX(parameters!$D$41:$AG$178,MATCH('PV (extension)'!B62,parameters!$C$41:$C$178,0),MATCH('PV (extension)'!A77,parameters!$D$5:$AG$5,0))/O77 -> 9.1929602e-05 | Q77: roof-top | R77: =INDEX(parameters!$C$196:$EJ$198,MATCH('PV (extension)'!Q77,parameters!$B$196:$B$198,0),MATCH('PV (extension)'!B62,parameters!$C$195:$EJ$195,0)) -> 1860.2687 | S77: 3 | T77: 30 | U77: =T77*S77*R77 -> 167424.18 | V77: =1/U77 -> 5.9728528e-06
A78: photovoltaic slanted-roof installation, 3 kWp, micro-Si, panel, mounted, on roof | B78: =P78*V78 -> 9.5456949e-09 | C78: RER | D78: unit | F78: technosphere | G78: 2 | H78: -18.729872 | I78: 0.097988942 | J78: (2,2,1,1,1,3); Calculation with average annual yield and share of technologies. Lifetime: 30a. | L78: photovoltaic slanted-roof installation, 3 kWp, micro-Si, panel, mounted, on roof | N78: all | O78: 1 | P78: =INDEX(parameters!$D$41:$AG$178,MATCH('PV (extension)'!B62,parameters!$C$41:$C$178,0),MATCH('PV (extension)'!A78,parameters!$D$5:$AG$5,0))/O78 -> 0.0015981802 | Q78: roof-top | R78: =INDEX(parameters!$C$196:$EJ$198,MATCH('PV (extension)'!Q78,parameters!$B$196:$B$198,0),MATCH('PV (extension)'!B62,parameters!$C$195:$EJ$195,0)) -> 1860.2687 | S78: 3 | T78: 30 | U78: =T78*S78*R78 -> 167424.18 | V78: =1/U78 -> 5.9728528e-06
A79: photovoltaic open ground installation, 570 kWp, CIS, on open ground | B79: =P79*V79 -> 2.9857771e-10 | C79: RER | D79: unit | F79: technosphere | G79: 2 | H79: -21.666568 | I79: 0.097988942 | J79: (2,2,1,1,1,3); Calculation with average annual yield and share of technologies. Lifetime: 30a. | L79: photovoltaic open ground installation, 570 kWp, CIS, on open ground | N79: all | O79: 1 | P79: =INDEX(parameters!$D$41:$AG$178,MATCH('PV (extension)'!B62,parameters!$C$41:$C$178,0),MATCH('PV (extension)'!A79,parameters!$D$5:$AG$5,0))/O79 -> 0.010104186 | Q79: central | R79: =INDEX(parameters!$C$196:$EJ$198,MATCH('PV (extension)'!Q79,parameters!$B$196:$B$198,0),MATCH('PV (extension)'!B62,parameters!$C$195:$EJ$195,0)) -> 1979.0093 | S79: 570 | T79: 30 | U79: =T79*S79*R79 -> 33841058 | V79: =1/U79 -> 2.9549903e-08
A80: photovoltaic open ground installation, 570 kWp, CdTe, on open ground | B80: =P80*V80 -> 2.1933289e-09 | C80: RER | D80: unit | F80: technosphere | G80: 2 | H80: -21.475526 | I80: 0.097988942 | J80: (2,2,1,1,1,3); Calculation with average annual yield and share of technologies. Lifetime: 30a. | L80: photovoltaic open ground installation, 570 kWp, CdTe, on open ground | N80: all | O80: 1 | P80: =INDEX(parameters!$D$41:$AG$178,MATCH('PV (extension)'!B62,parameters!$C$41:$C$178,0),MATCH('PV (extension)'!A80,parameters!$D$5:$AG$5,0))/O80 -> 0.07422457 | Q80: central | R80: =INDEX(parameters!$C$196:$EJ$198,MATCH('PV (extension)'!Q80,parameters!$B$196:$B$198,0),MATCH('PV (extension)'!B62,parameters!$C$195:$EJ$195,0)) -> 1979.0093 | S80: 570 | T80: 30 | U80: =T80*S80*R80 -> 33841058 | V80: =1/U80 -> 2.9549903e-08
A81: photovoltaic open ground installation, 570 kWp, micro-Si, on open ground | B81: =P81*V81 -> 2.3247729e-11 | C81: RER | D81: unit | F81: technosphere | G81: 2 | H81: -23.512407 | I81: 0.097988942 | J81: (2,2,1,1,1,3); Calculation with average annual yield and share of technologies. Lifetime: 30a. | L81: photovoltaic open ground installation, 570 kWp, micro-Si, on open ground | N81: all | O81: 1 | P81: =INDEX(parameters!$D$41:$AG$178,MATCH('PV (extension)'!B62,parameters!$C$41:$C$178,0),MATCH('PV (extension)'!A81,parameters!$D$5:$AG$5,0))/O81 -> 0.00078672777 | Q81: central | R81: =INDEX(parameters!$C$196:$EJ$198,MATCH('PV (extension)'!Q81,parameters!$B$196:$B$198,0),MATCH('PV (extension)'!B62,parameters!$C$195:$EJ$195,0)) -> 1979.0093 | S81: 570 | T81: 30 | U81: =T81*S81*R81 -> 33841058 | V81: =1/U81 -> 2.9549903e-08
A82: photovoltaic open ground installation, 570 kWp, multi-Si, on open ground | B82: =P82*V82 -> 7.7798342e-09 | C82: RER | D82: unit | F82: technosphere | G82: 2 | H82: -18.200823 | I82: 0.097988942 | J82: (2,2,1,1,1,3); Calculation with average annual yield and share of technologies. Lifetime: 30a. | L82: photovoltaic open ground installation, 570 kWp, multi-Si, on open ground | N82: all | O82: 1 | P82: =INDEX(parameters!$D$41:$AG$178,MATCH('PV (extension)'!B62,parameters!$C$41:$C$178,0),MATCH('PV (extension)'!A82,parameters!$D$5:$AG$5,0))/O82 -> 0.26327782 | Q82: central | R82: =INDEX(parameters!$C$196:$EJ$198,MATCH('PV (extension)'!Q82,parameters!$B$196:$B$198,0),MATCH('PV (extension)'!B62,parameters!$C$195:$EJ$195,0)) -> 1979.0093 | S82: 570 | T82: 30 | U82: =T82*S82*R82 -> 33841058 | V82: =1/U82 -> 2.9549903e-08
A83: photovoltaic open ground installation, 570 kWp, single-Si, on open ground | B83: =P83*V83 -> 4.126759e-09 | C83: RER | D83: unit | F83: technosphere | G83: 2 | H83: -18.836469 | I83: 0.097988942 | J83: (2,2,1,1,1,3); Calculation with average annual yield and share of technologies. Lifetime: 30a. | L83: photovoltaic open ground installation, 570 kWp, single-Si, on open ground | N83: all | O83: 1 | P83: =INDEX(parameters!$D$41:$AG$178,MATCH('PV (extension)'!B62,parameters!$C$41:$C$178,0),MATCH('PV (extension)'!A83,parameters!$D$5:$AG$5,0))/O83 -> 0.13965389 | Q83: central | R83: =INDEX(parameters!$C$196:$EJ$198,MATCH('PV (extension)'!Q83,parameters!$B$196:$B$198,0),MATCH('PV (extension)'!B62,parameters!$C$195:$EJ$195,0)) -> 1979.0093 | S83: 570 | T83: 30 | U83: =T83*S83*R83 -> 33841058 | V83: =1/U83 -> 2.9549903e-08
A84: photovoltaic slanted-roof installation, 93 kWp, multi-Si, laminated, integrated, on roof | B84: =P84*V84 -> 1.2734622e-09 | C84: CH | D84: unit | F84: technosphere | G84: 2 | H84: -20.65879 | I84: 0.097988942 | J84: (2,2,1,1,1,3); Calculation with average annual yield and share of technologies. Lifetime: 30a. | L84: photovoltaic slanted-roof installation, 93 kWp, multi-Si, laminated, integrated, on roof | N84: all | O84: 1 | P84: =INDEX(parameters!$D$41:$AG$178,MATCH('PV (extension)'!B62,parameters!$C$41:$C$178,0),MATCH('PV (extension)'!A84,parameters!$D$5:$AG$5,0))/O84 -> 0.0066094595 | Q84: roof-top | R84: =INDEX(parameters!$C$196:$EJ$198,MATCH('PV (extension)'!Q84,parameters!$B$196:$B$198,0),MATCH('PV (extension)'!B62,parameters!$C$195:$EJ$195,0)) -> 1860.2687 | S84: 93 | T84: 30 | U84: =T84*S84*R84 -> 5190149.7 | V84: =1/U84 -> 1.9267267e-07
A85: photovoltaic slanted-roof installation, 93 kWp, multi-Si, panel, mounted, on roof | B85: =P85*V85 -> 2.1593402e-08 | C85: CH | D85: unit | F85: technosphere | G85: 2 | H85: -17.84536 | I85: 0.097988942 | J85: (2,2,1,1,1,3); Calculation with average annual yield and share of technologies. Lifetime: 30a. | L85: photovoltaic slanted-roof installation, 93 kWp, multi-Si, panel, mounted, on roof | N85: all | O85: 1 | P85: =INDEX(parameters!$D$41:$AG$178,MATCH('PV (extension)'!B62,parameters!$C$41:$C$178,0),MATCH('PV (extension)'!A85,parameters!$D$5:$AG$5,0))/O85 -> 0.11207299 | Q85: roof-top | R85: =INDEX(parameters!$C$196:$EJ$198,MATCH('PV (extension)'!Q85,parameters!$B$196:$B$198,0),MATCH('PV (extension)'!B62,parameters!$C$195:$EJ$195,0)) -> 1860.2687 | S85: 93 | T85: 30 | U85: =T85*S85*R85 -> 5190149.7 | V85: =1/U85 -> 1.9267267e-07
A86: photovoltaic slanted-roof installation, 93 kWp, single-Si, laminated, integrated, on roof | B86: =P86*V86 -> 6.7320729e-10 | C86: CH | D86: unit | F86: technosphere | G86: 2 | H86: -21.294425 | I86: 0.097988942 | J86: (2,2,1,1,1,3); Calculation with average annual yield and share of technologies. Lifetime: 30a. | L86: photovoltaic slanted-roof installation, 93 kWp, single-Si, laminated, integrated, on roof | N86: all | O86: 1 | P86: =INDEX(parameters!$D$41:$AG$178,MATCH('PV (extension)'!B62,parameters!$C$41:$C$178,0),MATCH('PV (extension)'!A86,parameters!$D$5:$AG$5,0))/O86 -> 0.0034940466 | Q86: roof-top | R86: =INDEX(parameters!$C$196:$EJ$198,MATCH('PV (extension)'!Q86,parameters!$B$196:$B$198,0),MATCH('PV (extension)'!B62,parameters!$C$195:$EJ$195,0)) -> 1860.2687 | S86: 93 | T86: 30 | U86: =T86*S86*R86 -> 5190149.7 | V86: =1/U86 -> 1.9267267e-07
A87: photovoltaic slanted-roof installation, 93 kWp, single-Si, panel, mounted, on roof | B87: =P87*V87 -> 1.1310851e-08 | C87: CH | D87: unit | F87: technosphere | G87: 2 | H87: -18.481004 | I87: 0.097988942 | J87: (2,2,1,1,1,3); Calculation with average annual yield and share of technologies. Lifetime: 30a. | L87: photovoltaic slanted-roof installation, 93 kWp, single-Si, panel, mounted, on roof | N87: all | O87: 1 | P87: =INDEX(parameters!$D$41:$AG$178,MATCH('PV (extension)'!B62,parameters!$C$41:$C$178,0),MATCH('PV (extension)'!A87,parameters!$D$5:$AG$5,0))/O87 -> 0.05870501 | Q87: roof-top | R87: =INDEX(parameters!$C$196:$EJ$198,MATCH('PV (extension)'!Q87,parameters!$B$196:$B$198,0),MATCH('PV (extension)'!B62,parameters!$C$195:$EJ$195,0)) -> 1860.2687 | S87: 93 | T87: 30 | U87: =T87*S87*R87 -> 5190149.7 | V87: =1/U87 -> 1.9267267e-07
A88: photovoltaic facade installation, 3kWp, multi-Si, laminated, integrated, at building | B88: =P88*V88 -> 2.7957264e-08 | C88: APAC | D88: unit | F88: technosphere | G88: 2 | H88: -17.561299 | I88: 0.097988942 | J88: (2,2,1,1,1,3); Calculation with average annual yield and share of technologies. Lifetime: 30a. | L88: photovoltaic facade installation, 3kWp, multi-Si, laminated, integrated, at building | N88: all | O88: 1 | P88: =INDEX(parameters!$D$41:$AG$178,MATCH('PV (extension)'!B62,parameters!$C$41:$C$178,0),MATCH('PV (extension)'!A88,parameters!$D$5:$AG$5,0))/O88 -> 0.0032864644 | Q88: façade | R88: =INDEX(parameters!$C$196:$EJ$198,MATCH('PV (extension)'!Q88,parameters!$B$196:$B$198,0),MATCH('PV (extension)'!B62,parameters!$C$195:$EJ$195,0)) -> 1306.1461 | S88: 3 | T88: 30 | U88: =T88*S88*R88 -> 117553.15 | V88: =1/U88 -> 8.5067903e-06
A89: photovoltaic facade installation, 3kWp, multi-Si, panel, mounted, at building | B89: =P89*V89 -> 2.7418676e-08 | C89: APAC | D89: unit | F89: technosphere | G89: 2 | H89: -17.561299 | I89: 0.097988942 | J89: (2,2,1,1,1,3); Calculation with average annual yield and share of technologies. Lifetime: 30a. | L89: photovoltaic facade installation, 3kWp, multi-Si, panel, mounted, at building | N89: all | O89: 1 | P89: =INDEX(parameters!$D$41:$AG$178,MATCH('PV (extension)'!B62,parameters!$C$41:$C$178,0),MATCH('PV (extension)'!A89,parameters!$D$5:$AG$5,0))/O89 -> 0.0032231518 | Q89: façade | R89: =INDEX(parameters!$C$196:$EJ$198,MATCH('PV (extension)'!Q89,parameters!$B$196:$B$198,0),MATCH('PV (extension)'!B62,parameters!$C$195:$EJ$195,0)) -> 1306.1461 | S89: 3 | T89: 30 | U89: =T89*S89*R89 -> 117553.15 | V89: =1/U89 -> 8.5067903e-06
A90: photovoltaic facade installation, 3kWp, single-Si, laminated, integrated, at building | B90: =P90*V90 -> 1.4738757e-08 | C90: APAC | D90: unit | F90: technosphere | G90: 2 | H90: -18.196897 | I90: 0.097988942 | J90: (2,2,1,1,1,3); Calculation with average annual yield and share of technologies. Lifetime: 30a. | L90: photovoltaic facade installation, 3kWp, single-Si, laminated, integrated, at building | N90: all | O90: 1 | P90: =INDEX(parameters!$D$41:$AG$178,MATCH('PV (extension)'!B62,parameters!$C$41:$C$178,0),MATCH('PV (extension)'!A90,parameters!$D$5:$AG$5,0))/O90 -> 0.0017325874 | Q90: façade | R90: =INDEX(parameters!$C$196:$EJ$198,MATCH('PV (extension)'!Q90,parameters!$B$196:$B$198,0),MATCH('PV (extension)'!B62,parameters!$C$195:$EJ$195,0)) -> 1306.1461 | S90: 3 | T90: 30 | U90: =T90*S90*R90 -> 117553.15 | V90: =1/U90 -> 8.5067903e-06
A91: photovoltaic facade installation, 3kWp, single-Si, panel, mounted, at building | B91: =P91*V91 -> 1.4726005e-08 | C91: APAC | D91: unit | F91: technosphere | G91: 2 | H91: -18.196897 | I91: 0.097988942 | J91: (2,2,1,1,1,3); Calculation with average annual yield and share of technologies. Lifetime: 30a. | L91: photovoltaic facade installation, 3kWp, single-Si, panel, mounted, at building | N91: all | O91: 1 | P91: =INDEX(parameters!$D$41:$AG$178,MATCH('PV (extension)'!B62,parameters!$C$41:$C$178,0),MATCH('PV (extension)'!A91,parameters!$D$5:$AG$5,0))/O91 -> 0.0017310882 | Q91: façade | R91: =INDEX(parameters!$C$196:$EJ$198,MATCH('PV (extension)'!Q91,parameters!$B$196:$B$198,0),MATCH('PV (extension)'!B62,parameters!$C$195:$EJ$195,0)) -> 1306.1461 | S91: 3 | T91: 30 | U91: =T91*S91*R91 -> 117553.15 | V91: =1/U91 -> 8.5067903e-06
A92: photovoltaic flat-roof installation, 3kWp, multi-Si, on roof | B92: =P92*V92 -> 3.0237609e-07 | C92: APAC | D92: unit | F92: technosphere | G92: 2 | H92: -15.209918 | I92: 0.097988942 | J92: (2,2,1,1,1,3); Calculation with average annual yield and share of technologies. Lifetime: 30a. | L92: photovoltaic flat-roof installation, 3kWp, multi-Si, on roof | N92: all | O92: 1 | P92: =INDEX(parameters!$D$41:$AG$178,MATCH('PV (extension)'!B62,parameters!$C$41:$C$178,0),MATCH('PV (extension)'!A92,parameters!$D$5:$AG$5,0))/O92 -> 0.05062507 | Q92: roof-top | R92: =INDEX(parameters!$C$196:$EJ$198,MATCH('PV (extension)'!Q92,parameters!$B$196:$B$198,0),MATCH('PV (extension)'!B62,parameters!$C$195:$EJ$195,0)) -> 1860.2687 | S92: 3 | T92: 30 | U92: =T92*S92*R92 -> 167424.18 | V92: =1/U92 -> 5.9728528e-06
A93: photovoltaic flat-roof installation, 3kWp, single-Si, on roof | B93: =P93*V93 -> 1.5783594e-07 | C93: APAC | D93: unit | F93: technosphere | G93: 2 | H93: -15.845553 | I93: 0.097988942 | J93: (2,2,1,1,1,3); Calculation with average annual yield and share of technologies. Lifetime: 30a. | L93: photovoltaic flat-roof installation, 3kWp, single-Si, on roof | N93: all | O93: 1 | P93: =INDEX(parameters!$D$41:$AG$178,MATCH('PV (extension)'!B62,parameters!$C$41:$C$178,0),MATCH('PV (extension)'!A93,parameters!$D$5:$AG$5,0))/O93 -> 0.026425553 | Q93: roof-top | R93: =INDEX(parameters!$C$196:$EJ$198,MATCH('PV (extension)'!Q93,parameters!$B$196:$B$198,0),MATCH('PV (extension)'!B62,parameters!$C$195:$EJ$195,0)) -> 1860.2687 | S93: 3 | T93: 30 | U93: =T93*S93*R93 -> 167424.18 | V93: =1/U93 -> 5.9728528e-06
A94: photovoltaic slanted-roof installation, 3kWp, CIS, panel, mounted, on roof | B94: =P94*V94 -> 8.7301935e-08 | C94: CH | D94: unit | F94: technosphere | G94: 2 | H94: -16.88405 | I94: 0.097988942 | J94: (2,2,1,1,1,3); Calculation with average annual yield and share of technologies. Lifetime: 30a. | L94: photovoltaic slanted-roof installation, 3kWp, CIS, panel, mounted, on roof | N94: all | O94: 1 | P94: =INDEX(parameters!$D$41:$AG$178,MATCH('PV (extension)'!B62,parameters!$C$41:$C$178,0),MATCH('PV (extension)'!A94,parameters!$D$5:$AG$5,0))/O94 -> 0.014616455 | Q94: roof-top | R94: =INDEX(parameters!$C$196:$EJ$198,MATCH('PV (extension)'!Q94,parameters!$B$196:$B$198,0),MATCH('PV (extension)'!B62,parameters!$C$195:$EJ$195,0)) -> 1860.2687 | S94: 3 | T94: 30 | U94: =T94*S94*R94 -> 167424.18 | V94: =1/U94 -> 5.9728528e-06
A95: photovoltaic slanted-roof installation, 3kWp, CdTe, laminated, integrated, on roof | B95: =P95*V95 -> 2.4445089e-09 | C95: CH | D95: unit | F95: technosphere | G95: 2 | H95: -19.506397 | I95: 0.097988942 | J95: (2,2,1,1,1,3); Calculation with average annual yield and share of technologies. Lifetime: 30a. | L95: photovoltaic slanted-roof installation, 3kWp, CdTe, laminated, integrated, on roof | N95: all | O95: 1 | P95: =INDEX(parameters!$D$41:$AG$178,MATCH('PV (extension)'!B62,parameters!$C$41:$C$178,0),MATCH('PV (extension)'!A95,parameters!$D$5:$AG$5,0))/O95 -> 0.00040926991 | Q95: roof-top | R95: =INDEX(parameters!$C$196:$EJ$198,MATCH('PV (extension)'!Q95,parameters!$B$196:$B$198,0),MATCH('PV (extension)'!B62,parameters!$C$195:$EJ$195,0)) -> 1860.2687 | S95: 3 | T95: 30 | U95: =T95*S95*R95 -> 167424.18 | V95: =1/U95 -> 5.9728528e-06
A96: photovoltaic slanted-roof installation, 3kWp, multi-Si, laminated, integrated, on roof | B96: =P96*V96 -> 1.4522971e-08 | C96: APAC | D96: unit | F96: technosphere | G96: 2 | H96: -18.220765 | I96: 0.097988942 | J96: (2,2,1,1,1,3); Calculation with average annual yield and share of technologies. Lifetime: 30a. | L96: photovoltaic slanted-roof installation, 3kWp, multi-Si, laminated, integrated, on roof | N96: all | O96: 1 | P96: =INDEX(parameters!$D$41:$AG$178,MATCH('PV (extension)'!B62,parameters!$C$41:$C$178,0),MATCH('PV (extension)'!A96,parameters!$D$5:$AG$5,0))/O96 -> 0.0024314966 | Q96: roof-top | R96: =INDEX(parameters!$C$196:$EJ$198,MATCH('PV (extension)'!Q96,parameters!$B$196:$B$198,0),MATCH('PV (extension)'!B62,parameters!$C$195:$EJ$195,0)) -> 1860.2687 | S96: 3 | T96: 30 | U96: =T96*S96*R96 -> 167424.18 | V96: =1/U96 -> 5.9728528e-06
A97: photovoltaic slanted-roof installation, 3kWp, multi-Si, panel, mounted, on roof | B97: =P97*V97 -> 2.4858168e-07 | C97: APAC | D97: unit | F97: technosphere | G97: 2 | H97: -15.407354 | I97: 0.097988942 | J97: (2,2,1,1,1,3); Calculation with average annual yield and share of technologies. Lifetime: 30a. | L97: photovoltaic slanted-roof installation, 3kWp, multi-Si, panel, mounted, on roof | N97: all | O97: 1 | P97: =INDEX(parameters!$D$41:$AG$178,MATCH('PV (extension)'!B62,parameters!$C$41:$C$178,0),MATCH('PV (extension)'!A97,parameters!$D$5:$AG$5,0))/O97 -> 0.041618585 | Q97: roof-top | R97: =INDEX(parameters!$C$196:$EJ$198,MATCH('PV (extension)'!Q97,parameters!$B$196:$B$198,0),MATCH('PV (extension)'!B62,parameters!$C$195:$EJ$195,0)) -> 1860.2687 | S97: 3 | T97: 30 | U97: =T97*S97*R97 -> 167424.18 | V97: =1/U97 -> 5.9728528e-06
A98: photovoltaic slanted-roof installation, 3kWp, single-Si, laminated, integrated, on roof | B98: =P98*V98 -> 7.6753364e-09 | C98: APAC | D98: unit | F98: technosphere | G98: 2 | H98: -18.856368 | I98: 0.097988942 | J98: (2,2,1,1,1,3); Calculation with average annual yield and share of technologies. Lifetime: 30a. | L98: photovoltaic slanted-roof installation, 3kWp, single-Si, laminated, integrated, on roof | N98: all | O98: 1 | P98: =INDEX(parameters!$D$41:$AG$178,MATCH('PV (extension)'!B62,parameters!$C$41:$C$178,0),MATCH('PV (extension)'!A98,parameters!$D$5:$AG$5,0))/O98 -> 0.0012850369 | Q98: roof-top | R98: =INDEX(parameters!$C$196:$EJ$198,MATCH('PV (extension)'!Q98,parameters!$B$196:$B$198,0),MATCH('PV (extension)'!B62,parameters!$C$195:$EJ$195,0)) -> 1860.2687 | S98: 3 | T98: 30 | U98: =T98*S98*R98 -> 167424.18 | V98: =1/U98 -> 5.9728528e-06
A99: photovoltaic slanted-roof installation, 3kWp, single-Si, panel, mounted, on roof | B99: =P99*V99 -> 1.299105e-07 | C99: APAC | D99: unit | F99: technosphere | G99: 2 | H99: -16.042988 | I99: 0.097988942 | J99: (2,2,1,1,1,3); Calculation with average annual yield and share of technologies. Lifetime: 30a. | L99: photovoltaic slanted-roof installation, 3kWp, single-Si, panel, mounted, on roof | N99: all | O99: 1 | P99: =INDEX(parameters!$D$41:$AG$178,MATCH('PV (extension)'!B62,parameters!$C$41:$C$178,0),MATCH('PV (extension)'!A99,parameters!$D$5:$AG$5,0))/O99 -> 0.02175016 | Q99: roof-top | R99: =INDEX(parameters!$C$196:$EJ$198,MATCH('PV (extension)'!Q99,parameters!$B$196:$B$198,0),MATCH('PV (extension)'!B62,parameters!$C$195:$EJ$195,0)) -> 1860.2687 | S99: 3 | T99: 30 | U99: =T99*S99*R99 -> 167424.18 | V99: =1/U99 -> 5.9728528e-06
A100: market for tap water | B100: 0.0020721 | C100: Europe without Switzerland | D100: kilogram | F100: technosphere | G100: 2 | H100: -6.1791927 | I100: 0.043409846 | J100: (2,2,1,1,1,3); Estimation 20l/m2 panel | L100: tap water
A101: treatment of wastewater, from residence, capacity 1.1E10l/year | B101: -1.8649e-06 | C101: CH | D101: cubic meter | F101: technosphere | G101: 2 | H101: -13.192303 | I101: 0.043409846 | J101: (2,2,1,1,1,3); Estimation 20l/m2 panel | K101: TRUE | L101: wastewater, from residence
A103: Activity | B103: electricity production, photovoltaic, residential
...

Sheet parameters
A1: skip
B2: source | C2: https://www.researchgate.net/publication/347999880_Life_Cycle_Inventories_and_Life_Cycle_Assessments_of_Photovoltaic_Systems_2020_Task_12_PV_Sustainability?channel=doi&linkId=5fec5fa4a6fdccdcb81714bd&showFulltext=true
B4: shares | D4: Residential | V4: Commercial | AH4: Sum | AJ4: Production volumes (GWh, IRENA 2025)
D5: photovoltaic facade installation, 3kWp, single-Si, laminated, integrated, at building | E5: photovoltaic facade installation, 3kWp, single-Si, panel, mounted, at building | F5: photovoltaic facade installation, 3kWp, multi-Si, laminated, integrated, at building | G5: photovoltaic facade installation, 3kWp, multi-Si, panel, mounted, at building | H5: photovoltaic flat-roof installation, 3kWp, single-Si, on roof | I5: photovoltaic flat-roof installation, 3kWp, multi-Si, on roof | J5: photovoltaic slanted-roof installation, 3kWp, CdTe, laminated, integrated, on roof | K5: photovoltaic slanted-roof installation, 3 kWp, CdTe, panel, mounted, on roof | L5: photovoltaic slanted-roof installation, 3 kWp, CIS, laminated, integrated, on roof | M5: photovoltaic slanted-roof installation, 3kWp, CIS, panel, mounted, on roof | N5: photovoltaic slanted-roof installation, 3 kWp, micro-Si, laminated, integrated, on roof | O5: photovoltaic slanted-roof installation, 3 kWp, micro-Si, panel, mounted, on roof | P5: photovoltaic slanted-roof installation, 3kWp, single-Si, laminated, integrated, on roof | Q5: photovoltaic slanted-roof installation, 3kWp, single-Si, panel, mounted, on roof | R5: photovoltaic slanted-roof installation, 3kWp, multi-Si, laminated, integrated, on roof | S5: photovoltaic slanted-roof installation, 3kWp, multi-Si, panel, mounted, on roof | T5: sum | V5: photovoltaic flat-roof installation, 156 kWp, single-Si, on roof | W5: photovoltaic flat-roof installation, 156 kWp, multi-Si, on roof | X5: photovoltaic slanted-roof installation, 93 kWp, single-Si, laminated, integrated, on roof | Y5: photovoltaic slanted-roof installation, 93 kWp, single-Si, panel, mounted, on roof | Z5: photovoltaic slanted-roof installation, 93 kWp, multi-Si, laminated, integrated, on roof | AA5: photovoltaic slanted-roof installation, 93 kWp, multi-Si, panel, mounted, on roof | AB5: photovoltaic open ground installation, 570 kWp, single-Si, on open ground | AC5: photovoltaic open ground installation, 570 kWp, multi-Si, on open ground | AD5: photovoltaic open ground installation, 570 kWp, CdTe, on open ground | AE5: photovoltaic open ground installation, 570 kWp, CIS, on open ground | AF5: photovoltaic open ground installation, 570 kWp, micro-Si, on open ground | AG5: sum
B6: Australia | C6: AU | D6: 0.00255 | E6: 0.00255 | F6: 0.00482 | G6: 0.00482 | H6: 0.0383 | I6: 0.0723 | J6: 0.000984 | K6: 0.0164 | L6: 0.000813 | M6: 0.0136 | N6: 0.000128 | O6: 0.00214 | P6: 0.00189 | Q6: 0.0314 | R6: 0.00356 | S6: 0.0593 | T6: =SUM(D6:S6) -> 0.255555 | V6: 0.0766 | W6: 0.145 | X6: 0.00511 | Y6: 0.0851 | Z6: 0.00964 | AA6: 0.161 | AB6: 0.0868 | AC6: 0.164 | AD6: 0.0062 | AE6: 0.00512 | AF6: 0.000808 | AG6: =SUM(V6:AF6) -> 0.745378 | AH6: =SUM(V6:AF6,D6:S6) -> 1.000933 | AJ6: =VLOOKUP(C6,'extension - production vol'!$B$6:$D$235,3,0) -> 41964.6
B7: Austria | C7: AT | D7: 0.000419 | E7: 0 | F7: 0.00643 | G7: 0 | H7: 0.00998 | I7: 0.153 | J7: 0.000301 | K7: 0.00992 | L7: 0.000249 | M7: 0.0082 | N7: 3.93e-05 | O7: 0.00129 | P7: 0.000267 | Q7: 0.00879 | R7: 0.00409 | S7: 0.135 | T7: =SUM(D7:S7) -> 0.3379753 | V7: 0.02 | W7: 0.306 | X7: 0.000606 | Y7: 0.02 | Z7: 0.00929 | AA7: 0.306 | AB7: 0 | AC7: 0 | AD7: 0 | AE7: 0 | AF7: 0 | AG7: =SUM(V7:AF7) -> 0.661896 | AH7: =SUM(V7:AF7,D7:S7) -> 0.9998713 | AJ7: =VLOOKUP(C7,'extension - production vol'!$B$6:$D$235,3,0) -> 6394.811
B8: Belgium | C8: BE | D8: 0.00285 | E8: 0.00285 | F8: 0.00537 | G8: 0.00537 | H8: 0.0427 | I8: 0.0806 | J8: 0.0011 | K8: 0.0183 | L8: 0.000906 | M8: 0.0151 | N8: 0.000143 | O8: 0.00239 | P8: 0.0021 | Q8: 0.035 | R8: 0.00397 | S8: 0.0662 | T8: =SUM(D8:S8) -> 0.284949 | V8: 0.0854 | W8: 0.161 | X8: 0.00569 | Y8: 0.0948 | Z8: 0.0107 | AA8: 0.179 | AB8: 0.0588 | AC8: 0.111 | AD8: 0.0042 | AE8: 0.00347 | AF8: 0.000548 | AG8: =SUM(V8:AF8) -> 0.714608 | AH8: =SUM(V8:AF8,D8:S8) -> 0.999557 | AJ8: =VLOOKUP(C8,'extension - production vol'!$B$6:$D$235,3,0) -> 7820
B9: Canada | C9: CA | D9: 0.00121 | E9: 0.00121 | F9: 0.00229 | G9: 0.00229 | H9: 0.0182 | I9: 0.0344 | J9: 0.000468 | K9: 0.0078 | L9: 0.000387 | M9: 0.00645 | N9: 6.11e-05 | O9: 0.00102 | P9: 0.000897 | Q9: 0.0149 | R9: 0.00169 | S9: 0.0282 | T9: =SUM(D9:S9) -> 0.1214731 | V9: 0.0364 | W9: 0.0688 | X9: 0.00243 | Y9: 0.0405 | Z9: 0.00459 | AA9: 0.0764 | AB9: 0.214 | AC9: 0.405 | AD9: 0.0153 | AE9: 0.0127 | AF9: 0.002 | AG9: =SUM(V9:AF9) -> 0.87812 | AH9: =SUM(V9:AF9,D9:S9) -> 0.9995931 | AJ9: =VLOOKUP(C9,'extension - production vol'!$B$6:$D$235,3,0) -> 7071
B10: Chile | C10: CL | D10: 3.21e-05 | E10: 3.21e-05 | F10: 6.07e-05 | G10: 6.07e-05 | H10: 0.000482 | I10: 0.00091 | J10: 1.24e-05 | K10: 0.000206 | L10: 1.02e-05 | M10: 0.000171 | N10: 1.62e-06 | O10: 2.69e-05 | P10: 2.37e-05 | Q10: 0.000396 | R10: 4.48e-05 | S10: 0.000747 | T10: =SUM(D10:S10) -> 0.00321722 | V10: 0.000964 | W10: 0.00182 | X10: 6.43e-05 | Y10: 0.00107 | Z10: 0.000121 | AA10: 0.00202 | AB10: 0.327 | AC10: 0.618 | AD10: 0.0234 | AE10: 0.0193 | AF10: 0.00305 | AG10: =SUM(V10:AF10) -> 0.9968093 | AH10: =SUM(V10:AF10,D10:S10) -> 1.0000265 | AJ10: =VLOOKUP(C10,'extension - production vol'!$B$6:$D$235,3,0) -> 3.649
B11: China | C11: CN | D11: 0.001 | E11: 0.001 | F11: 0.00189 | G11: 0.00189 | H11: 0.015 | I11: 0.0284 | J11: 0.000168 | K11: 0.00279 | L11: 0.000138 | M11: 0.00231 | N11: 2.19e-05 | O11: 0.000364 | P11: 0.000889 | Q11: 0.0148 | R11: 0.00168 | S11: 0.028 | T11: =SUM(D11:S11) -> 0.1003409 | V11: 0.0301 | W11: 0.0568 | X11: 0.00201 | Y11: 0.0334 | Z11: 0.00379 | AA11: 0.0631 | AB11: 0.241 | AC11: 0.455 | AD11: 0.00726 | AE11: 0.006 | AF11: 0.000947 | AG11: =SUM(V11:AF11) -> 0.899407 | AH11: =SUM(V11:AF11,D11:S11) -> 0.9997479 | AJ11: =VLOOKUP(C11,'extension - production vol'!$B$6:$D$235,3,0) -> 575.118
B12: Czech | C12: CZ | D12: 0.00216 | E12: 0.00216 | F12: 0.00408 | G12: 0.00408 | H12: 0.0324 | I12: 0.0612 | J12: 0.000833 | K12: 0.0139 | L12: 0.000688 | M12: 0.0115 | N12: 0.000109 | O12: 0.00181 | P12: 0.0016 | Q12: 0.0266 | R12: 0.00301 | S12: 0.0502 | T12: =SUM(D12:S12) -> 0.21633 | V12: 0.0648 | W12: 0.122 | X12: 0.00432 | Y12: 0.072 | Z12: 0.00816 | AA12: 0.136 | AB12: 0.124 | AC12: 0.235 | AD12: 0.00887 | AE12: 0.00733 | AF12: 0.00116 | AG12: =SUM(V12:AF12) -> 0.78364 | AH12: =SUM(V12:AF12,D12:S12) -> 0.99997 | AJ12: =VLOOKUP(C12,'extension - production vol'!$B$6:$D$235,3,0) -> 2892.093
B13: Denmark | C13: DK | D13: 0.00254 | E13: 0.00254 | F13: 0.0048 | G13: 0.0048 | H13: 0.0381 | I13: 0.0719 | J13: 0.000979 | K13: 0.0163 | L13: 0.000809 | M13: 0.0135 | N13: 0.000128 | O13: 0.00213 | P13: 0.00188 | Q13: 0.0313 | R13: 0.00354 | S13: 0.059 | T13: =SUM(D13:S13) -> 0.254246 | V13: 0.0762 | W13: 0.144 | X13: 0.00508 | Y13: 0.0847 | Z13: 0.00959 | AA13: 0.16 | AB13: 0.088 | AC13: 0.166 | AD13: 0.00629 | AE13: 0.00519 | AF13: 0.00082 | AG13: =SUM(V13:AF13) -> 0.74587 | AH13: =SUM(V13:AF13,D13:S13) -> 1.000116 | AJ13: =VLOOKUP(C13,'extension - production vol'!$B$6:$D$235,3,0) -> 3363.278
B14: Finland | C14: FI | D14: 0.00346 | E14: 0.00346 | F14: 0.00654 | G14: 0.00654 | H14: 0.0519 | I14: 0.0981 | J14: 0.00134 | K14: 0.0223 | L14: 0.0011 | M14: 0.0184 | N14: 0.000174 | O14: 0.0029 | P14: 0.00256 | Q14: 0.0426 | R14: 0.00483 | S14: 0.0805 | T14: =SUM(D14:S14) -> 0.346704 | V14: 0.104 | W14: 0.196 | X14: 0.00692 | Y14: 0.115 | Z14: 0.0131 | AA14: 0.218 | AB14: 0 | AC14: 0 | AD14: 0 | AE14: 0 | AF14: 0 | AG14: =SUM(V14:AF14) -> 0.65302 | AH14: =SUM(V14:AF14,D14:S14) -> 0.999724 | AJ14: =VLOOKUP(C14,'extension - production vol'!$B$6:$D$235,3,0) -> 716.44
B15: France | C15: FR | D15: 0.00207 | E15: 0.00207 | F15: 0.00391 | G15: 0.00391 | H15: 0.0311 | I15: 0.0587 | J15: 0.000799 | K15: 0.0133 | L15: 0.00066 | M15: 0.011 | N15: 0.000104 | O15: 0.00174 | P15: 0.00153 | Q15: 0.0255 | R15: 0.00289 | S15: 0.0481 | T15: =SUM(D15:S15) -> 0.207383 | V15: 0.0621 | W15: 0.117 | X15: 0.00414 | Y15: 0.069 | Z15: 0.00782 | AA15: 0.13 | AB15: 0.133 | AC15: 0.251 | AD15: 0.00948 | AE15: 0.00783 | AF15: 0.00124 | AG15: =SUM(V15:AF15) -> 0.79261 | AH15: =SUM(V15:AF15,D15:S15) -> 0.999993 | AJ15: =VLOOKUP(C15,'extension - production vol'!$B$6:$D$235,3,0) -> 302.606
B16: Germany | C16: DE | D16: 0.00258 | E16: 0.00258 | F16: 0.00487 | G16: 0.00487 | H16: 0.0387 | I16: 0.0731 | J16: 0.000995 | K16: 0.0166 | L16: 0.000822 | M16: 0.0137 | N16: 0.00013 | O16: 0.00216 | P16: 0.00191 | Q16: 0.0318 | R16: 0.0036 | S16: 0.06 | T16: =SUM(D16:S16) -> 0.258417 | V16: 0.0774 | W16: 0.146 | X16: 0.00516 | Y16: 0.086 | Z16: 0.00974 | AA16: 0.162 | AB16: 0.0841 | AC16: 0.159 | AD16: 0.00601 | AE16: 0.00496 | AF16: 0.000784 | AG16: =SUM(V16:AF16) -> 0.741154 | AH16: =SUM(V16:AF16,D16:S16) -> 0.999571 | AJ16: =VLOOKUP(C16,'extension - production vol'!$B$6:$D$235,3,0) -> 63576
B17: Greece | C17: GR | D17: 0.00216 | E17: 0.00216 | F17: 0.00408 | G17: 0.00408 | H17: 0.0324 | I17: 0.0612 | J17: 0.000833 | K17: 0.0139 | L17: 0.000688 | M17: 0.0115 | N17: 0.000109 | O17: 0.00181 | P17: 0.0016 | Q17: 0.0266 | R17: 0.00301 | S17: 0.0502 | T17: =SUM(D17:S17) -> 0.21633 | V17: 0.0648 | W17: 0.122 | X17: 0.00432 | Y17: 0.072 | Z17: 0.00816 | AA17: 0.136 | AB17: 0.124 | AC17: 0.235 | AD17: 0.00887 | AE17: 0.00733 | AF17: 0.00116 | AG17: =SUM(V17:AF17) -> 0.78364 | AH17: =SUM(V17:AF17,D17:S17) -> 0.99997 | AJ17: =VLOOKUP(C17,'extension - production vol'!$B$6:$D$235,3,0) -> 8893.572
... B38: USA | C38: US | D38: 0.00143 | E38: 0.00143 | F38: 0.00259 | G38: 0.00259 | H38: 0.0213 | I38: 0.0385 | J38: 5.77e-05 | K38: 0.00139 | L38: 0.000113 | M38: 0.00271 | N38: 7.72e-05 | O38: 0.00185 | P38: 0.000933 | Q38: 0.0224 | R38: 0.00168 | S38: 0.0404 | T38: =SUM(D38:S38) -> 0.1394509 | V38: 0.0427 | W38: 0.077 | X38: 0.00204 | Y38: 0.049 | Z38: 0.00368 | AA38: 0.0884 | AB38: 0.138 | AC38: 0.26 | AD38: 0.195 | AE38: 0.00506 | AF38: 0 | AG38: =SUM(V38:AF38) -> 0.86088 | AH38: =SUM(V38:AF38,D38:S38) -> 1.0003309 | AJ38: =VLOOKUP(C38,'extension - production vol'!$B$6:$D$235,3,0) -> 214436.07
B40: EXTENSION following the method of the IEA PVPS 2020 report, but WITHOUT technology split. Technology split derived as weighted average from data above.
B41: =VLOOKUP(C41,'extension - productivity'!A7:B182,2,0) -> Namibia | C41: NA | D41: =SUMPRODUCT(D$6:D$38,$AJ$6:$AJ$38)/SUM($AJ$6:$AJ$38) -> 0.0017325874 | E41: =SUMPRODUCT(E$6:E$38,$AJ$6:$AJ$38)/SUM($AJ$6:$AJ$38) -> 0.0017310882 | F41: =SUMPRODUCT(F$6:F$38,$AJ$6:$AJ$38)/SUM($AJ$6:$AJ$38) -> 0.0032864644 | G41: =SUMPRODUCT(G$6:G$38,$AJ$6:$AJ$38)/SUM($AJ$6:$AJ$38) -> 0.0032231518 | H41: =SUMPRODUCT(H$6:H$38,$AJ$6:$AJ$38)/SUM($AJ$6:$AJ$38) -> 0.026425553 | I41: =SUMPRODUCT(I$6:I$38,$AJ$6:$AJ$38)/SUM($AJ$6:$AJ$38) -> 0.05062507 | J41: =SUMPRODUCT(J$6:J$38,$AJ$6:$AJ$38)/SUM($AJ$6:$AJ$38) -> 0.00040926991 | K41: =SUMPRODUCT(K$6:K$38,$AJ$6:$AJ$38)/SUM($AJ$6:$AJ$38) -> 0.0059328609 | ... S41: =SUMPRODUCT(S$6:S$38,$AJ$6:$AJ$38)/SUM($AJ$6:$AJ$38) -> 0.041618585 | T41: =SUMPRODUCT($T$6:$T$38,$AJ$6:$AJ$38)/SUM($AJ$6:$AJ$38) -> 0.17766752 | V41: =SUMPRODUCT(V$6:V$38,$AJ$6:$AJ$38)/SUM($AJ$6:$AJ$38) -> 0.052740019 | W41: =SUMPRODUCT(W$6:W$38,$AJ$6:$AJ$38)/SUM($AJ$6:$AJ$38) -> 0.10096416 | X41: =SUMPRODUCT(X$6:X$38,$AJ$6:$AJ$38)/SUM($AJ$6:$AJ$38) -> 0.0034940466 | Y41: =SUMPRODUCT(Y$6:Y$38,$AJ$6:$AJ$38)/SUM($AJ$6:$AJ$38) -> 0.05870501 | Z41: =SUMPRODUCT(Z$6:Z$38,$AJ$6:$AJ$38)/SUM($AJ$6:$AJ$38) -> 0.0066094595 | AA41: =SUMPRODUCT(AA$6:AA$38,$AJ$6:$AJ$38)/SUM($AJ$6:$AJ$38) -> 0.11207299 | AB41: =SUMPRODUCT(AB$6:AB$38,$AJ$6:$AJ$38)/SUM($AJ$6:$AJ$38) -> 0.13965389 | AC41: =SUMPRODUCT(AC$6:AC$38,$AJ$6:$AJ$38)/SUM($AJ$6:$AJ$38) -> 0.26327782 | ... AF41: =SUMPRODUCT(AF$6:AF$38,$AJ$6:$AJ$38)/SUM($AJ$6:$AJ$38) -> 0.00078672777 | AG41: =1-T41 -> 0.82233248
B42: =VLOOKUP(C42,'extension - productivity'!A8:B183,2,0) -> Egypt | C42: EG | D42: =SUMPRODUCT(D$6:D$38,$AJ$6:$AJ$38)/SUM($AJ$6:$AJ$38) -> 0.0017325874 | E42: =SUMPRODUCT(E$6:E$38,$AJ$6:$AJ$38)/SUM($AJ$6:$AJ$38) -> 0.0017310882 | F42: =SUMPRODUCT(F$6:F$38,$AJ$6:$AJ$38)/SUM($AJ$6:$AJ$38) -> 0.0032864644 | G42: =SUMPRODUCT(G$6:G$38,$AJ$6:$AJ$38)/SUM($AJ$6:$AJ$38) -> 0.0032231518 | H42: =SUMPRODUCT(H$6:H$38,$AJ$6:$AJ$38)/SUM($AJ$6:$AJ$38) -> 0.026425553 | I42: =SUMPRODUCT(I$6:I$38,$AJ$6:$AJ$38)/SUM($AJ$6:$AJ$38) -> 0.05062507 | J42: =SUMPRODUCT(J$6:J$38,$AJ$6:$AJ$38)/SUM($AJ$6:$AJ$38) -> 0.00040926991 | K42: =SUMPRODUCT(K$6:K$38,$AJ$6:$AJ$38)/SUM($AJ$6:$AJ$38) -> 0.0059328609 | ... S42: =SUMPRODUCT(S$6:S$38,$AJ$6:$AJ$38)/SUM($AJ$6:$AJ$38) -> 0.041618585 | T42: =SUMPRODUCT($T$6:$T$38,$AJ$6:$AJ$38)/SUM($AJ$6:$AJ$38) -> 0.17766752 | V42: =SUMPRODUCT(V$6:V$38,$AJ$6:$AJ$38)/SUM($AJ$6:$AJ$38) -> 0.052740019 | W42: =SUMPRODUCT(W$6:W$38,$AJ$6:$AJ$38)/SUM($AJ$6:$AJ$38) -> 0.10096416 | X42: =SUMPRODUCT(X$6:X$38,$AJ$6:$AJ$38)/SUM($AJ$6:$AJ$38) -> 0.0034940466 | Y42: =SUMPRODUCT(Y$6:Y$38,$AJ$6:$AJ$38)/SUM($AJ$6:$AJ$38) -> 0.05870501 | Z42: =SUMPRODUCT(Z$6:Z$38,$AJ$6:$AJ$38)/SUM($AJ$6:$AJ$38) -> 0.0066094595 | AA42: =SUMPRODUCT(AA$6:AA$38,$AJ$6:$AJ$38)/SUM($AJ$6:$AJ$38) -> 0.11207299 | AB42: =SUMPRODUCT(AB$6:AB$38,$AJ$6:$AJ$38)/SUM($AJ$6:$AJ$38) -> 0.13965389 | AC42: =SUMPRODUCT(AC$6:AC$38,$AJ$6:$AJ$38)/SUM($AJ$6:$AJ$38) -> 0.26327782 | ... AF42: =SUMPRODUCT(AF$6:AF$38,$AJ$6:$AJ$38)/SUM($AJ$6:$AJ$38) -> 0.00078672777 | AG42: =1-T42 -> 0.82233248
B43: =VLOOKUP(C43,'extension - productivity'!A9:B184,2,0) -> Jordan | C43: JO | D43: =SUMPRODUCT(D$6:D$38,$AJ$6:$AJ$38)/SUM($AJ$6:$AJ$38) -> 0.0017325874 | E43: =SUMPRODUCT(E$6:E$38,$AJ$6:$AJ$38)/SUM($AJ$6:$AJ$38) -> 0.0017310882 | F43: =SUMPRODUCT(F$6:F$38,$AJ$6:$AJ$38)/SUM($AJ$6:$AJ$38) -> 0.0032864644 | G43: =SUMPRODUCT(G$6:G$38,$AJ$6:$AJ$38)/SUM($AJ$6:$AJ$38) -> 0.0032231518 | H43: =SUMPRODUCT(H$6:H$38,$AJ$6:$AJ$38)/SUM($AJ$6:$AJ$38) -> 0.026425553 | I43: =SUMPRODUCT(I$6:I$38,$AJ$6:$AJ$38)/SUM($AJ$6:$AJ$38) -> 0.05062507 | J43: =SUMPRODUCT(J$6:J$38,$AJ$6:$AJ$38)/SUM($AJ$6:$AJ$38) -> 0.00040926991 | K43: =SUMPRODUCT(K$6:K$38,$AJ$6:$AJ$38)/SUM($AJ$6:$AJ$38) -> 0.0059328609 | ... S43: =SUMPRODUCT(S$6:S$38,$AJ$6:$AJ$38)/SUM($AJ$6:$AJ$38) -> 0.041618585 | T43: =SUMPRODUCT($T$6:$T$38,$AJ$6:$AJ$38)/SUM($AJ$6:$AJ$38) -> 0.17766752 | V43: =SUMPRODUCT(V$6:V$38,$AJ$6:$AJ$38)/SUM($AJ$6:$AJ$38) -> 0.052740019 | W43: =SUMPRODUCT(W$6:W$38,$AJ$6:$AJ$38)/SUM($AJ$6:$AJ$38) -> 0.10096416 | X43: =SUMPRODUCT(X$6:X$38,$AJ$6:$AJ$38)/SUM($AJ$6:$AJ$38) -> 0.0034940466 | Y43: =SUMPRODUCT(Y$6:Y$38,$AJ$6:$AJ$38)/SUM($AJ$6:$AJ$38) -> 0.05870501 | Z43: =SUMPRODUCT(Z$6:Z$38,$AJ$6:$AJ$38)/SUM($AJ$6:$AJ$38) -> 0.0066094595 | AA43: =SUMPRODUCT(AA$6:AA$38,$AJ$6:$AJ$38)/SUM($AJ$6:$AJ$38) -> 0.11207299 | AB43: =SUMPRODUCT(AB$6:AB$38,$AJ$6:$AJ$38)/SUM($AJ$6:$AJ$38) -> 0.13965389 | AC43: =SUMPRODUCT(AC$6:AC$38,$AJ$6:$AJ$38)/SUM($AJ$6:$AJ$38) -> 0.26327782 | ... AF43: =SUMPRODUCT(AF$6:AF$38,$AJ$6:$AJ$38)/SUM($AJ$6:$AJ$38) -> 0.00078672777 | AG43: =1-T43 -> 0.82233248
B44: =VLOOKUP(C44,'extension - productivity'!A10:B185,2,0) -> Libya | C44: LY | D44: =SUMPRODUCT(D$6:D$38,$AJ$6:$AJ$38)/SUM($AJ$6:$AJ$38) -> 0.0017325874 | E44: =SUMPRODUCT(E$6:E$38,$AJ$6:$AJ$38)/SUM($AJ$6:$AJ$38) -> 0.0017310882 | F44: =SUMPRODUCT(F$6:F$38,$AJ$6:$AJ$38)/SUM($AJ$6:$AJ$38) -> 0.0032864644 | G44: =SUMPRODUCT(G$6:G$38,$AJ$6:$AJ$38)/SUM($AJ$6:$AJ$38) -> 0.0032231518 | H44: =SUMPRODUCT(H$6:H$38,$AJ$6:$AJ$38)/SUM($AJ$6:$AJ$38) -> 0.026425553 | I44: =SUMPRODUCT(I$6:I$38,$AJ$6:$AJ$38)/SUM($AJ$6:$AJ$38) -> 0.05062507 | J44: =SUMPRODUCT(J$6:J$38,$AJ$6:$AJ$38)/SUM($AJ$6:$AJ$38) -> 0.00040926991 | K44: =SUMPRODUCT(K$6:K$38,$AJ$6:$AJ$38)/SUM($AJ$6:$AJ$38) -> 0.0059328609 | ... S44: =SUMPRODUCT(S$6:S$38,$AJ$6:$AJ$38)/SUM($AJ$6:$AJ$38) -> 0.041618585 | T44: =SUMPRODUCT($T$6:$T$38,$AJ$6:$AJ$38)/SUM($AJ$6:$AJ$38) -> 0.17766752 | V44: =SUMPRODUCT(V$6:V$38,$AJ$6:$AJ$38)/SUM($AJ$6:$AJ$38) -> 0.052740019 | W44: =SUMPRODUCT(W$6:W$38,$AJ$6:$AJ$38)/SUM($AJ$6:$AJ$38) -> 0.10096416 | X44: =SUMPRODUCT(X$6:X$38,$AJ$6:$AJ$38)/SUM($AJ$6:$AJ$38) -> 0.0034940466 | Y44: =SUMPRODUCT(Y$6:Y$38,$AJ$6:$AJ$38)/SUM($AJ$6:$AJ$38) -> 0.05870501 | Z44: =SUMPRODUCT(Z$6:Z$38,$AJ$6:$AJ$38)/SUM($AJ$6:$AJ$38) -> 0.0066094595 | AA44: =SUMPRODUCT(AA$6:AA$38,$AJ$6:$AJ$38)/SUM($AJ$6:$AJ$38) -> 0.11207299 | AB44: =SUMPRODUCT(AB$6:AB$38,$AJ$6:$AJ$38)/SUM($AJ$6:$AJ$38) -> 0.13965389 | AC44: =SUMPRODUCT(AC$6:AC$38,$AJ$6:$AJ$38)/SUM($AJ$6:$AJ$38) -> 0.26327782 | ... AF44: =SUMPRODUCT(AF$6:AF$38,$AJ$6:$AJ$38)/SUM($AJ$6:$AJ$38) -> 0.00078672777 | AG44: =1-T44 -> 0.82233248
B45: =VLOOKUP(C45,'extension - productivity'!A11:B186,2,0) -> Yemen | C45: YE | D45: =SUMPRODUCT(D$6:D$38,$AJ$6:$AJ$38)/SUM($AJ$6:$AJ$38) -> 0.0017325874 | E45: =SUMPRODUCT(E$6:E$38,$AJ$6:$AJ$38)/SUM($AJ$6:$AJ$38) -> 0.0017310882 | F45: =SUMPRODUCT(F$6:F$38,$AJ$6:$AJ$38)/SUM($AJ$6:$AJ$38) -> 0.0032864644 | G45: =SUMPRODUCT(G$6:G$38,$AJ$6:$AJ$38)/SUM($AJ$6:$AJ$38) -> 0.0032231518 | H45: =SUMPRODUCT(H$6:H$38,$AJ$6:$AJ$38)/SUM($AJ$6:$AJ$38) -> 0.026425553 | I45: =SUMPRODUCT(I$6:I$38,$AJ$6:$AJ$38)/SUM($AJ$6:$AJ$38) -> 0.05062507 | J45: =SUMPRODUCT(J$6:J$38,$AJ$6:$AJ$38)/SUM($AJ$6:$AJ$38) -> 0.00040926991 | K45: =SUMPRODUCT(K$6:K$38,$AJ$6:$AJ$38)/SUM($AJ$6:$AJ$38) -> 0.0059328609 | ... S45: =SUMPRODUCT(S$6:S$38,$AJ$6:$AJ$38)/SUM($AJ$6:$AJ$38) -> 0.041618585 | T45: =SUMPRODUCT($T$6:$T$38,$AJ$6:$AJ$38)/SUM($AJ$6:$AJ$38) -> 0.17766752 | V45: =SUMPRODUCT(V$6:V$38,$AJ$6:$AJ$38)/SUM($AJ$6:$AJ$38) -> 0.052740019 | W45: =SUMPRODUCT(W$6:W$38,$AJ$6:$AJ$38)/SUM($AJ$6:$AJ$38) -> 0.10096416 | X45: =SUMPRODUCT(X$6:X$38,$AJ$6:$AJ$38)/SUM($AJ$6:$AJ$38) -> 0.0034940466 | Y45: =SUMPRODUCT(Y$6:Y$38,$AJ$6:$AJ$38)/SUM($AJ$6:$AJ$38) -> 0.05870501 | Z45: =SUMPRODUCT(Z$6:Z$38,$AJ$6:$AJ$38)/SUM($AJ$6:$AJ$38) -> 0.0066094595 | AA45: =SUMPRODUCT(AA$6:AA$38,$AJ$6:$AJ$38)/SUM($AJ$6:$AJ$38) -> 0.11207299 | AB45: =SUMPRODUCT(AB$6:AB$38,$AJ$6:$AJ$38)/SUM($AJ$6:$AJ$38) -> 0.13965389 | AC45: =SUMPRODUCT(AC$6:AC$38,$AJ$6:$AJ$38)/SUM($AJ$6:$AJ$38) -> 0.26327782 | ... AF45: =SUMPRODUCT(AF$6:AF$38,$AJ$6:$AJ$38)/SUM($AJ$6:$AJ$38) -> 0.00078672777 | AG45: =1-T45 -> 0.82233248
B46: =VLOOKUP(C46,'extension - productivity'!A12:B187,2,0) -> Saudi Arabia | C46: SA | D46: =SUMPRODUCT(D$6:D$38,$AJ$6:$AJ$38)/SUM($AJ$6:$AJ$38) -> 0.0017325874 | E46: =SUMPRODUCT(E$6:E$38,$AJ$6:$AJ$38)/SUM($AJ$6:$AJ$38) -> 0.0017310882 | F46: =SUMPRODUCT(F$6:F$38,$AJ$6:$AJ$38)/SUM($AJ$6:$AJ$38) -> 0.0032864644 | G46: =SUMPRODUCT(G$6:G$38,$AJ$6:$AJ$38)/SUM($AJ$6:$AJ$38) -> 0.0032231518 | H46: =SUMPRODUCT(H$6:H$38,$AJ$6:$AJ$38)/SUM($AJ$6:$AJ$38) -> 0.026425553 | I46: =SUMPRODUCT(I$6:I$38,$AJ$6:$AJ$38)/SUM($AJ$6:$AJ$38) -> 0.05062507 | J46: =SUMPRODUCT(J$6:J$38,$AJ$6:$AJ$38)/SUM($AJ$6:$AJ$38) -> 0.00040926991 | K46: =SUMPRODUCT(K$6:K$38,$AJ$6:$AJ$38)/SUM($AJ$6:$AJ$38) -> 0.0059328609 | ... S46: =SUMPRODUCT(S$6:S$38,$AJ$6:$AJ$38)/SUM($AJ$6:$AJ$38) -> 0.041618585 | T46: =SUMPRODUCT($T$6:$T$38,$AJ$6:$AJ$38)/SUM($AJ$6:$AJ$38) -> 0.17766752 | V46: =SUMPRODUCT(V$6:V$38,$AJ$6:$AJ$38)/SUM($AJ$6:$AJ$38) -> 0.052740019 | W46: =SUMPRODUCT(W$6:W$38,$AJ$6:$AJ$38)/SUM($AJ$6:$AJ$38) -> 0.10096416 | X46: =SUMPRODUCT(X$6:X$38,$AJ$6:$AJ$38)/SUM($AJ$6:$AJ$38) -> 0.0034940466 | Y46: =SUMPRODUCT(Y$6:Y$38,$AJ$6:$AJ$38)/SUM($AJ$6:$AJ$38) -> 0.05870501 | Z46: =SUMPRODUCT(Z$6:Z$38,$AJ$6:$AJ$38)/SUM($AJ$6:$AJ$38) -> 0.0066094595 | AA46: =SUMPRODUCT(AA$6:AA$38,$AJ$6:$AJ$38)/SUM($AJ$6:$AJ$38) -> 0.11207299 | AB46: =SUMPRODUCT(AB$6:AB$38,$AJ$6:$AJ$38)/SUM($AJ$6:$AJ$38) -> 0.13965389 | AC46: =SUMPRODUCT(AC$6:AC$38,$AJ$6:$AJ$38)/SUM($AJ$6:$AJ$38) -> 0.26327782 | ... AF46: =SUMPRODUCT(AF$6:AF$38,$AJ$6:$AJ$38)/SUM($AJ$6:$AJ$38) -> 0.00078672777 | AG46: =1-T46 -> 0.82233248
B47: =VLOOKUP(C47,'extension - productivity'!A13:B188,2,0) -> Western Sahara | C47: EH | D47: =SUMPRODUCT(D$6:D$38,$AJ$6:$AJ$38)/SUM($AJ$6:$AJ$38) -> 0.0017325874 | E47: =SUMPRODUCT(E$6:E$38,$AJ$6:$AJ$38)/SUM($AJ$6:$AJ$38) -> 0.0017310882 | F47: =SUMPRODUCT(F$6:F$38,$AJ$6:$AJ$38)/SUM($AJ$6:$AJ$38) -> 0.0032864644 | G47: =SUMPRODUCT(G$6:G$38,$AJ$6:$AJ$38)/SUM($AJ$6:$AJ$38) -> 0.0032231518 | H47: =SUMPRODUCT(H$6:H$38,$AJ$6:$AJ$38)/SUM($AJ$6:$AJ$38) -> 0.026425553 | I47: =SUMPRODUCT(I$6:I$38,$AJ$6:$AJ$38)/SUM($AJ$6:$AJ$38) -> 0.05062507 | J47: =SUMPRODUCT(J$6:J$38,$AJ$6:$AJ$38)/SUM($AJ$6:$AJ$38) -> 0.00040926991 | K47: =SUMPRODUCT(K$6:K$38,$AJ$6:$AJ$38)/SUM($AJ$6:$AJ$38) -> 0.0059328609 | ... S47: =SUMPRODUCT(S$6:S$38,$AJ$6:$AJ$38)/SUM($AJ$6:$AJ$38) -> 0.041618585 | T47: =SUMPRODUCT($T$6:$T$38,$AJ$6:$AJ$38)/SUM($AJ$6:$AJ$38) -> 0.17766752 | V47: =SUMPRODUCT(V$6:V$38,$AJ$6:$AJ$38)/SUM($AJ$6:$AJ$38) -> 0.052740019 | W47: =SUMPRODUCT(W$6:W$38,$AJ$6:$AJ$38)/SUM($AJ$6:$AJ$38) -> 0.10096416 | X47: =SUMPRODUCT(X$6:X$38,$AJ$6:$AJ$38)/SUM($AJ$6:$AJ$38) -> 0.0034940466 | Y47: =SUMPRODUCT(Y$6:Y$38,$AJ$6:$AJ$38)/SUM($AJ$6:$AJ$38) -> 0.05870501 | Z47: =SUMPRODUCT(Z$6:Z$38,$AJ$6:$AJ$38)/SUM($AJ$6:$AJ$38) -> 0.0066094595 | AA47: =SUMPRODUCT(AA$6:AA$38,$AJ$6:$AJ$38)/SUM($AJ$6:$AJ$38) -> 0.11207299 | AB47: =SUMPRODUCT(AB$6:AB$38,$AJ$6:$AJ$38)/SUM($AJ$6:$AJ$38) -> 0.13965389 | AC47: =SUMPRODUCT(AC$6:AC$38,$AJ$6:$AJ$38)/SUM($AJ$6:$AJ$38) -> 0.26327782 | ... AF47: =SUMPRODUCT(AF$6:AF$38,$AJ$6:$AJ$38)/SUM($AJ$6:$AJ$38) -> 0.00078672777 | AG47: =1-T47 -> 0.82233248
B48: =VLOOKUP(C48,'extension - productivity'!A14:B189,2,0) -> Botswana | C48: BW | D48: =SUMPRODUCT(D$6:D$38,$AJ$6:$AJ$38)/SUM($AJ$6:$AJ$38) -> 0.0017325874 | E48: =SUMPRODUCT(E$6:E$38,$AJ$6:$AJ$38)/SUM($AJ$6:$AJ$38) -> 0.0017310882 | F48: =SUMPRODUCT(F$6:F$38,$AJ$6:$AJ$38)/SUM($AJ$6:$AJ$38) -> 0.0032864644 | G48: =SUMPRODUCT(G$6:G$38,$AJ$6:$AJ$38)/SUM($AJ$6:$AJ$38) -> 0.0032231518 | H48: =SUMPRODUCT(H$6:H$38,$AJ$6:$AJ$38)/SUM($AJ$6:$AJ$38) -> 0.026425553 | I48: =SUMPRODUCT(I$6:I$38,$AJ$6:$AJ$38)/SUM($AJ$6:$AJ$38) -> 0.05062507 | J48: =SUMPRODUCT(J$6:J$38,$AJ$6:$AJ$38)/SUM($AJ$6:$AJ$38) -> 0.00040926991 | K48: =SUMPRODUCT(K$6:K$38,$AJ$6:$AJ$38)/SUM($AJ$6:$AJ$38) -> 0.0059328609 | ... S48: =SUMPRODUCT(S$6:S$38,$AJ$6:$AJ$38)/SUM($AJ$6:$AJ$38) -> 0.041618585 | T48: =SUMPRODUCT($T$6:$T$38,$AJ$6:$AJ$38)/SUM($AJ$6:$AJ$38) -> 0.17766752 | V48: =SUMPRODUCT(V$6:V$38,$AJ$6:$AJ$38)/SUM($AJ$6:$AJ$38) -> 0.052740019 | W48: =SUMPRODUCT(W$6:W$38,$AJ$6:$AJ$38)/SUM($AJ$6:$AJ$38) -> 0.10096416 | X48: =SUMPRODUCT(X$6:X$38,$AJ$6:$AJ$38)/SUM($AJ$6:$AJ$38) -> 0.0034940466 | Y48: =SUMPRODUCT(Y$6:Y$38,$AJ$6:$AJ$38)/SUM($AJ$6:$AJ$38) -> 0.05870501 | Z48: =SUMPRODUCT(Z$6:Z$38,$AJ$6:$AJ$38)/SUM($AJ$6:$AJ$38) -> 0.0066094595 | AA48: =SUMPRODUCT(AA$6:AA$38,$AJ$6:$AJ$38)/SUM($AJ$6:$AJ$38) -> 0.11207299 | AB48: =SUMPRODUCT(AB$6:AB$38,$AJ$6:$AJ$38)/SUM($AJ$6:$AJ$38) -> 0.13965389 | AC48: =SUMPRODUCT(AC$6:AC$38,$AJ$6:$AJ$38)/SUM($AJ$6:$AJ$38) -> 0.26327782 | ... AF48: =SUMPRODUCT(AF$6:AF$38,$AJ$6:$AJ$38)/SUM($AJ$6:$AJ$38) -> 0.00078672777 | AG48: =1-T48 -> 0.82233248
B49: =VLOOKUP(C49,'extension - productivity'!A15:B190,2,0) -> Oman | C49: OM | D49: =SUMPRODUCT(D$6:D$38,$AJ$6:$AJ$38)/SUM($AJ$6:$AJ$38) -> 0.0017325874 | E49: =SUMPRODUCT(E$6:E$38,$AJ$6:$AJ$38)/SUM($AJ$6:$AJ$38) -> 0.0017310882 | F49: =SUMPRODUCT(F$6:F$38,$AJ$6:$AJ$38)/SUM($AJ$6:$AJ$38) -> 0.0032864644 | G49: =SUMPRODUCT(G$6:G$38,$AJ$6:$AJ$38)/SUM($AJ$6:$AJ$38) -> 0.0032231518 | H49: =SUMPRODUCT(H$6:H$38,$AJ$6:$AJ$38)/SUM($AJ$6:$AJ$38) -> 0.026425553 | I49: =SUMPRODUCT(I$6:I$38,$AJ$6:$AJ$38)/SUM($AJ$6:$AJ$38) -> 0.05062507 | J49: =SUMPRODUCT(J$6:J$38,$AJ$6:$AJ$38)/SUM($AJ$6:$AJ$38) -> 0.00040926991 | K49: =SUMPRODUCT(K$6:K$38,$AJ$6:$AJ$38)/SUM($AJ$6:$AJ$38) -> 0.0059328609 | ... S49: =SUMPRODUCT(S$6:S$38,$AJ$6:$AJ$38)/SUM($AJ$6:$AJ$38) -> 0.041618585 | T49: =SUMPRODUCT($T$6:$T$38,$AJ$6:$AJ$38)/SUM($AJ$6:$AJ$38) -> 0.17766752 | V49: =SUMPRODUCT(V$6:V$38,$AJ$6:$AJ$38)/SUM($AJ$6:$AJ$38) -> 0.052740019 | W49: =SUMPRODUCT(W$6:W$38,$AJ$6:$AJ$38)/SUM($AJ$6:$AJ$38) -> 0.10096416 | X49: =SUMPRODUCT(X$6:X$38,$AJ$6:$AJ$38)/SUM($AJ$6:$AJ$38) -> 0.0034940466 | Y49: =SUMPRODUCT(Y$6:Y$38,$AJ$6:$AJ$38)/SUM($AJ$6:$AJ$38) -> 0.05870501 | Z49: =SUMPRODUCT(Z$6:Z$38,$AJ$6:$AJ$38)/SUM($AJ$6:$AJ$38) -> 0.0066094595 | AA49: =SUMPRODUCT(AA$6:AA$38,$AJ$6:$AJ$38)/SUM($AJ$6:$AJ$38) -> 0.11207299 | AB49: =SUMPRODUCT(AB$6:AB$38,$AJ$6:$AJ$38)/SUM($AJ$6:$AJ$38) -> 0.13965389 | AC49: =SUMPRODUCT(AC$6:AC$38,$AJ$6:$AJ$38)/SUM($AJ$6:$AJ$38) -> 0.26327782 | ... AF49: =SUMPRODUCT(AF$6:AF$38,$AJ$6:$AJ$38)/SUM($AJ$6:$AJ$38) -> 0.00078672777 | AG49: =1-T49 -> 0.82233248
B50: =VLOOKUP(C50,'extension - productivity'!A16:B191,2,0) -> Algeria | C50: DZ | D50: =SUMPRODUCT(D$6:D$38,$AJ$6:$AJ$38)/SUM($AJ$6:$AJ$38) -> 0.0017325874 | E50: =SUMPRODUCT(E$6:E$38,$AJ$6:$AJ$38)/SUM($AJ$6:$AJ$38) -> 0.0017310882 | F50: =SUMPRODUCT(F$6:F$38,$AJ$6:$AJ$38)/SUM($AJ$6:$AJ$38) -> 0.0032864644 | G50: =SUMPRODUCT(G$6:G$38,$AJ$6:$AJ$38)/SUM($AJ$6:$AJ$38) -> 0.0032231518 | H50: =SUMPRODUCT(H$6:H$38,$AJ$6:$AJ$38)/SUM($AJ$6:$AJ$38) -> 0.026425553 | I50: =SUMPRODUCT(I$6:I$38,$AJ$6:$AJ$38)/SUM($AJ$6:$AJ$38) -> 0.05062507 | J50: =SUMPRODUCT(J$6:J$38,$AJ$6:$AJ$38)/SUM($AJ$6:$AJ$38) -> 0.00040926991 | K50: =SUMPRODUCT(K$6:K$38,$AJ$6:$AJ$38)/SUM($AJ$6:$AJ$38) -> 0.0059328609 | ... S50: =SUMPRODUCT(S$6:S$38,$AJ$6:$AJ$38)/SUM($AJ$6:$AJ$38) -> 0.041618585 | T50: =SUMPRODUCT($T$6:$T$38,$AJ$6:$AJ$38)/SUM($AJ$6:$AJ$38) -> 0.17766752 | V50: =SUMPRODUCT(V$6:V$38,$AJ$6:$AJ$38)/SUM($AJ$6:$AJ$38) -> 0.052740019 | W50: =SUMPRODUCT(W$6:W$38,$AJ$6:$AJ$38)/SUM($AJ$6:$AJ$38) -> 0.10096416 | X50: =SUMPRODUCT(X$6:X$38,$AJ$6:$AJ$38)/SUM($AJ$6:$AJ$38) -> 0.0034940466 | Y50: =SUMPRODUCT(Y$6:Y$38,$AJ$6:$AJ$38)/SUM($AJ$6:$AJ$38) -> 0.05870501 | Z50: =SUMPRODUCT(Z$6:Z$38,$AJ$6:$AJ$38)/SUM($AJ$6:$AJ$38) -> 0.0066094595 | AA50: =SUMPRODUCT(AA$6:AA$38,$AJ$6:$AJ$38)/SUM($AJ$6:$AJ$38) -> 0.11207299 | AB50: =SUMPRODUCT(AB$6:AB$38,$AJ$6:$AJ$38)/SUM($AJ$6:$AJ$38) -> 0.13965389 | AC50: =SUMPRODUCT(AC$6:AC$38,$AJ$6:$AJ$38)/SUM($AJ$6:$AJ$38) -> 0.26327782 | ... AF50: =SUMPRODUCT(AF$6:AF$38,$AJ$6:$AJ$38)/SUM($AJ$6:$AJ$38) -> 0.00078672777 | AG50: =1-T50 -> 0.82233248
B51: =VLOOKUP(C51,'extension - productivity'!A17:B192,2,0) -> Sudan | C51: SD | D51: =SUMPRODUCT(D$6:D$38,$AJ$6:$AJ$38)/SUM($AJ$6:$AJ$38) -> 0.0017325874 | E51: =SUMPRODUCT(E$6:E$38,$AJ$6:$AJ$38)/SUM($AJ$6:$AJ$38) -> 0.0017310882 | F51: =SUMPRODUCT(F$6:F$38,$AJ$6:$AJ$38)/SUM($AJ$6:$AJ$38) -> 0.0032864644 | G51: =SUMPRODUCT(G$6:G$38,$AJ$6:$AJ$38)/SUM($AJ$6:$AJ$38) -> 0.0032231518 | H51: =SUMPRODUCT(H$6:H$38,$AJ$6:$AJ$38)/SUM($AJ$6:$AJ$38) -> 0.026425553 | I51: =SUMPRODUCT(I$6:I$38,$AJ$6:$AJ$38)/SUM($AJ$6:$AJ$38) -> 0.05062507 | J51: =SUMPRODUCT(J$6:J$38,$AJ$6:$AJ$38)/SUM($AJ$6:$AJ$38) -> 0.00040926991 | K51: =SUMPRODUCT(K$6:K$38,$AJ$6:$AJ$38)/SUM($AJ$6:$AJ$38) -> 0.0059328609 | ... S51: =SUMPRODUCT(S$6:S$38,$AJ$6:$AJ$38)/SUM($AJ$6:$AJ$38) -> 0.041618585 | T51: =SUMPRODUCT($T$6:$T$38,$AJ$6:$AJ$38)/SUM($AJ$6:$AJ$38) -> 0.17766752 | V51: =SUMPRODUCT(V$6:V$38,$AJ$6:$AJ$38)/SUM($AJ$6:$AJ$38) -> 0.052740019 | W51: =SUMPRODUCT(W$6:W$38,$AJ$6:$AJ$38)/SUM($AJ$6:$AJ$38) -> 0.10096416 | X51: =SUMPRODUCT(X$6:X$38,$AJ$6:$AJ$38)/SUM($AJ$6:$AJ$38) -> 0.0034940466 | Y51: =SUMPRODUCT(Y$6:Y$38,$AJ$6:$AJ$38)/SUM($AJ$6:$AJ$38) -> 0.05870501 | Z51: =SUMPRODUCT(Z$6:Z$38,$AJ$6:$AJ$38)/SUM($AJ$6:$AJ$38) -> 0.0066094595 | AA51: =SUMPRODUCT(AA$6:AA$38,$AJ$6:$AJ$38)/SUM($AJ$6:$AJ$38) -> 0.11207299 | AB51: =SUMPRODUCT(AB$6:AB$38,$AJ$6:$AJ$38)/SUM($AJ$6:$AJ$38) -> 0.13965389 | AC51: =SUMPRODUCT(AC$6:AC$38,$AJ$6:$AJ$38)/SUM($AJ$6:$AJ$38) -> 0.26327782 | ... AF51: =SUMPRODUCT(AF$6:AF$38,$AJ$6:$AJ$38)/SUM($AJ$6:$AJ$38) -> 0.00078672777 | AG51: =1-T51 -> 0.82233248
B52: =VLOOKUP(C52,'extension - productivity'!A18:B193,2,0) -> Lesotho | C52: LS | D52: =SUMPRODUCT(D$6:D$38,$AJ$6:$AJ$38)/SUM($AJ$6:$AJ$38) -> 0.0017325874 | E52: =SUMPRODUCT(E$6:E$38,$AJ$6:$AJ$38)/SUM($AJ$6:$AJ$38) -> 0.0017310882 | F52: =SUMPRODUCT(F$6:F$38,$AJ$6:$AJ$38)/SUM($AJ$6:$AJ$38) -> 0.0032864644 | G52: =SUMPRODUCT(G$6:G$38,$AJ$6:$AJ$38)/SUM($AJ$6:$AJ$38) -> 0.0032231518 | H52: =SUMPRODUCT(H$6:H$38,$AJ$6:$AJ$38)/SUM($AJ$6:$AJ$38) -> 0.026425553 | I52: =SUMPRODUCT(I$6:I$38,$AJ$6:$AJ$38)/SUM($AJ$6:$AJ$38) -> 0.05062507 | J52: =SUMPRODUCT(J$6:J$38,$AJ$6:$AJ$38)/SUM($AJ$6:$AJ$38) -> 0.00040926991 | K52: =SUMPRODUCT(K$6:K$38,$AJ$6:$AJ$38)/SUM($AJ$6:$AJ$38) -> 0.0059328609 | ... S52: =SUMPRODUCT(S$6:S$38,$AJ$6:$AJ$38)/SUM($AJ$6:$AJ$38) -> 0.041618585 | T52: =SUMPRODUCT($T$6:$T$38,$AJ$6:$AJ$38)/SUM($AJ$6:$AJ$38) -> 0.17766752 | V52: =SUMPRODUCT(V$6:V$38,$AJ$6:$AJ$38)/SUM($AJ$6:$AJ$38) -> 0.052740019 | W52: =SUMPRODUCT(W$6:W$38,$AJ$6:$AJ$38)/SUM($AJ$6:$AJ$38) -> 0.10096416 | X52: =SUMPRODUCT(X$6:X$38,$AJ$6:$AJ$38)/SUM($AJ$6:$AJ$38) -> 0.0034940466 | Y52: =SUMPRODUCT(Y$6:Y$38,$AJ$6:$AJ$38)/SUM($AJ$6:$AJ$38) -> 0.05870501 | Z52: =SUMPRODUCT(Z$6:Z$38,$AJ$6:$AJ$38)/SUM($AJ$6:$AJ$38) -> 0.0066094595 | AA52: =SUMPRODUCT(AA$6:AA$38,$AJ$6:$AJ$38)/SUM($AJ$6:$AJ$38) -> 0.11207299 | AB52: =SUMPRODUCT(AB$6:AB$38,$AJ$6:$AJ$38)/SUM($AJ$6:$AJ$38) -> 0.13965389 | AC52: =SUMPRODUCT(AC$6:AC$38,$AJ$6:$AJ$38)/SUM($AJ$6:$AJ$38) -> 0.26327782 | ... AF52: =SUMPRODUCT(AF$6:AF$38,$AJ$6:$AJ$38)/SUM($AJ$6:$AJ$38) -> 0.00078672777 | AG52: =1-T52 -> 0.82233248
... B178: =VLOOKUP(C178,'extension - productivity'!A144:B319,2,0) -> Russia | C178: RU | D178: =SUMPRODUCT(D$6:D$38,$AJ$6:$AJ$38)/SUM($AJ$6:$AJ$38) -> 0.0017325874 | E178: =SUMPRODUCT(E$6:E$38,$AJ$6:$AJ$38)/SUM($AJ$6:$AJ$38) -> 0.0017310882 | F178: =SUMPRODUCT(F$6:F$38,$AJ$6:$AJ$38)/SUM($AJ$6:$AJ$38) -> 0.0032864644 | G178: =SUMPRODUCT(G$6:G$38,$AJ$6:$AJ$38)/SUM($AJ$6:$AJ$38) -> 0.0032231518 | H178: =SUMPRODUCT(H$6:H$38,$AJ$6:$AJ$38)/SUM($AJ$6:$AJ$38) -> 0.026425553 | I178: =SUMPRODUCT(I$6:I$38,$AJ$6:$AJ$38)/SUM($AJ$6:$AJ$38) -> 0.05062507 | J178: =SUMPRODUCT(J$6:J$38,$AJ$6:$AJ$38)/SUM($AJ$6:$AJ$38) -> 0.00040926991 | K178: =SUMPRODUCT(K$6:K$38,$AJ$6:$AJ$38)/SUM($AJ$6:$AJ$38) -> 0.0059328609 | ... S178: =SUMPRODUCT(S$6:S$38,$AJ$6:$AJ$38)/SUM($AJ$6:$AJ$38) -> 0.041618585 | T178: =SUMPRODUCT($T$6:$T$38,$AJ$6:$AJ$38)/SUM($AJ$6:$AJ$38) -> 0.17766752 | V178: =SUMPRODUCT(V$6:V$38,$AJ$6:$AJ$38)/SUM($AJ$6:$AJ$38) -> 0.052740019 | W178: =SUMPRODUCT(W$6:W$38,$AJ$6:$AJ$38)/SUM($AJ$6:$AJ$38) -> 0.10096416 | X178: =SUMPRODUCT(X$6:X$38,$AJ$6:$AJ$38)/SUM($AJ$6:$AJ$38) -> 0.0034940466 | Y178: =SUMPRODUCT(Y$6:Y$38,$AJ$6:$AJ$38)/SUM($AJ$6:$AJ$38) -> 0.05870501 | Z178: =SUMPRODUCT(Z$6:Z$38,$AJ$6:$AJ$38)/SUM($AJ$6:$AJ$38) -> 0.0066094595 | AA178: =SUMPRODUCT(AA$6:AA$38,$AJ$6:$AJ$38)/SUM($AJ$6:$AJ$38) -> 0.11207299 | AB178: =SUMPRODUCT(AB$6:AB$38,$AJ$6:$AJ$38)/SUM($AJ$6:$AJ$38) -> 0.13965389 | AC178: =SUMPRODUCT(AC$6:AC$38,$AJ$6:$AJ$38)/SUM($AJ$6:$AJ$38) -> 0.26327782 | ... AF178: =SUMPRODUCT(AF$6:AF$38,$AJ$6:$AJ$38)/SUM($AJ$6:$AJ$38) -> 0.00078672777 | AG178: =1-T178 -> 0.82233248
B181: lifetime | C181: 30 | D181: years
B182: production [kWh/kWp] | C182: PT | D182: IL | E182: SE | F182: FR | G182: TR | H182: NZ | I182: MY | J182: CN | K182: TH | L182: ZA | M182: JP | N182: CH | O182: DE | P182: KR | Q182: AT | R182: GR | S182: IE | T182: AU | U182: IT | V182: MX | W182: NL | X182: GB | Y182: ES | Z182: CL | AA182: HU | AB182: CZ | AC182: CA | AD182: US | AE182: NO | AF182: FI | AG182: BE | AH182: DK | AI182: LU
B183: roof-top | C183: 1427 | D183: 1695 | E183: 919 | F183: 968 | G183: 1388 | H183: 1240 | I183: 1332 | J183: 971 | K183: 1436 | L183: 1634 | M183: 1024 | N183: 976 | O183: 922 | P183: 1129 | Q183: 1044 | R183: 1323 | S183: 796 | T183: 1240 | U183: 1298 | V183: 1612 | W183: 937 | X183: 848 | Y183: 1423 | Z183: 1603 | AA183: 1090 | AB183: 944 | AC183: 1173 | AD183: 1401 | AE183: 832 | AF183: 891 | AG183: 908 | AH183: 971 | AI183: 908
B184: façade | C184: 999 | D184: 1187 | E184: 643 | F184: 678 | G184: 971 | H184: 868 | I184: 933 | J184: 679 | K184: 1005 | L184: 1144 | M184: 717 | N184: 683 | O184: 645 | P184: 790 | Q184: 731 | R184: 926 | S184: 557 | T184: 868 | U184: 908 | V184: 1128 | W184: 656 | X184: 593 | Y184: 996 | Z184: 1122 | AA184: 763 | AB184: 661 | AC184: 821 | AD184: 981 | AE184: 583 | AF184: 624 | AG184: 635 | AH184: 680 | AI184: 635
B185: central | C185: 1513 | D185: 1798 | E185: 974 | F185: 1026 | G185: 1471 | H185: 1315 | I185: 1413 | J185: 1029 | K185: 1522 | L185: 1733 | M185: 1086 | N185: 1040 | O185: 978 | P185: 1197 | Q185: 1111 | R185: 1402 | S185: 844 | T185: 1314 | U185: 1376 | V185: 1709 | W185: 994 | X185: 899 | Y185: 1509 | Z185: 1699 | AA185: 1156 | AB185: 1101 | AC185: 1243 | AD185: 1485 | AE185: 882 | AF185: 945 | AG185: 962 | AH185: 1030 | AI185: 962
B188: Correction factors for roof-top and facade compared to central
B189: production [kWh/kWp] | C189: PT | D189: IL | E189: SE | F189: FR | G189: TR | H189: NZ | I189: MY | J189: CN | K189: TH | L189: ZA | M189: JP | N189: CH | O189: DE | P189: KR | Q189: AT | R189: GR | S189: IE | T189: AU | U189: IT | V189: MX | W189: NL | X189: GB | Y189: ES | Z189: CL | AA189: HU | AB189: CZ | AC189: CA | AD189: US | AE189: NO | AF189: FI | AG189: BE | AH189: DK | AI189: LU
B190: roof-top | C190: =C183/C185 -> 0.94315929 | D190: =D183/D185 -> 0.94271413 | E190: =E183/E185 -> 0.94353183 | F190: =F183/F185 -> 0.94346979 | G190: =G183/G185 -> 0.9435758 | H190: =H183/H185 -> 0.94296578 | I190: =I183/I185 -> 0.94267516 | J190: =J183/J185 -> 0.9436346 | ... AI190: =AI183/AI185 -> 0.94386694
B191: façade | C191: =C184/C185 -> 0.66027759 | D191: =D184/D185 -> 0.66017798 | E191: =E184/E185 -> 0.66016427 | F191: =F184/F185 -> 0.66081871 | G191: =G184/G185 -> 0.66009517 | H191: =H184/H185 -> 0.66007605 | I191: =I184/I185 -> 0.66029724 | J191: =J184/J185 -> 0.65986395 | ... AI191: =AI184/AI185 -> 0.66008316
B192: central | C192: 1 | D192: 1 | E192: 1 | F192: 1 | G192: 1 | H192: 1 | I192: 1 | J192: 1 | K192: 1 | L192: 1 | M192: 1 | N192: 1 | O192: 1 | P192: 1 | Q192: 1 | R192: 1 | S192: 1 | T192: 1 | U192: 1 | V192: 1 | W192: 1 | X192: 1 | Y192: 1 | Z192: 1 | AA192: 1 | AB192: 1 | AC192: 1 | AD192: 1 | AE192: 1 | AF192: 1 | AG192: 1 | AH192: 1 | AI192: 1
B194: Countries extension (productivity figures from Global Solar Atlas)
B195: production [kWh/kWp] | C195: NA | D195: EG | E195: JO | F195: LY | G195: YE | H195: SA | I195: EH | J195: BW | K195: OM | L195: DZ | M195: SD | N195: LS | O195: MA | P195: NE | Q195: TD | R195: AE | S195: AF | T195: MR | U195: QA | V195: PS | W195: SY | X195: IR | Y195: ZW | Z195: ER | AA195: ZM | AB195: ML | AC195: KW | AD195: TN | AE195: MN | AF195: DJ | AG195: IQ | AH195: SV | AI195: LB | AJ195: MG | AK195: AO | AL195: ET | AM195: CY | AN195: PK | AO195: SO | AP195: MW | AQ195: SN | AR195: BF | AS195: GM | AT195: HT | AU195: AR | AV195: KE | AW195: TZ | AX195: CU | AY195: BO | AZ195: CF | BA195: GW | BB195: DO | BC195: UG | BD195: SS | BE195: MZ | BF195: GN | BG195: BS | BH195: TM | BI195: TJ | BJ195: PR | BK195: SZ | BL195: NG | BM195: JM | BN195: UZ | BO195: TL | BP195: GT | BQ195: IN | BR195: UY | BS195: BR | BT195: NP | BU195: PY | BV195: BJ | BW195: VE | BX195: CM | BY195: SR | BZ195: BI | CA195: HN | CB195: PE | CC195: LK | CD195: TT | CE195: CD | CF195: KH | CG195: TG | CH195: AM | CI195: BZ | CJ195: KG | CK195: SL | CL195: NI | CM195: GY | CN195: RW | CO195: GH | CP195: CI | CQ195: MM | CR195: GL | CS195: AL | CT195: BN | CU195: KP | CV195: CR | CW195: BD | CX195: LR | CY195: MK | CZ195: CG | DA195: PH | DB195: AZ | DC195: CO | DD195: KZ | DE195: LA | DF195: PA | DG195: ME | DH195: BG | DI195: BT | DJ195: ID | DK195: NC | DL195: PG | DM195: GQ | DN195: GA | DO195: HR | DP195: GE | DQ195: SB | DR195: RS | DS195: FJ | DT195: BA | DU195: VU | DV195: RO | DW195: CN-TW | DX195: VN | DY195: MD | DZ195: SI | EA195: EC | EB195: UA | EC195: SK | ED195: FK | EE195: PL | EF195: BY | EG195: LT | EH195: LV | EI195: EE | EJ195: RU
B196: roof-top | C196: =0.94*C198 -> 1860.2687 | D196: =0.94*D198 -> 1840.939 | E196: =0.94*E198 -> 1829.819 | F196: =0.94*F198 -> 1825.9674 | G196: =0.94*G198 -> 1799.4912 | H196: =0.94*H198 -> 1781.8009 | I196: =0.94*I198 -> 1781.2732 | J196: =0.94*J198 -> 1780.9017 | ... EJ196: =0.94*EJ198 -> 717.95394
B197: façade | C197: =0.66*C198 -> 1306.1461 | D197: =0.66*D198 -> 1292.5742 | E197: =0.66*E198 -> 1284.7665 | F197: =0.66*F198 -> 1282.0622 | G197: =0.66*G198 -> 1263.4725 | H197: =0.66*H198 -> 1251.0517 | I197: =0.66*I198 -> 1250.6812 | J197: =0.66*J198 -> 1250.4203 | ... EJ197: =0.66*EJ198 -> 504.09532
B198: central | C198: 1979.0093 | D198: 1958.4458 | E198: 1946.616 | F198: 1942.5185 | G198: 1914.3523 | H198: 1895.5329 | I198: 1894.9715 | J198: 1894.5763 | K198: 1888.512 | L198: 1874.3373 | M198: 1862.6667 | N198: 1858.0166 | O198: 1845.8179 | P198: 1844.0493 | Q198: 1834.9098 | R198: 1831.0609 | S198: 1821.0703 | T198: 1806.0932 | U198: 1797.0891 | V198: 1795.1818 | W198: 1792.984 | X198: 1789.3842 | Y198: 1785.8334 | Z198: 1779.986 | AA198: 1773.5096 | AB198: 1764.6415 | AC198: 1761.5088 | AD198: 1759.9738 | AE198: 1754.1327 | AF198: 1753.4368 | AG198: 1752.251 | AH198: 1750.1411 | AI198: 1743.7679 | AJ198: 1732.7701 | AK198: 1713.6276 | AL198: 1711.3513 | AM198: 1706.4762 | AN198: 1704.3105 | AO198: 1690.755 | AP198: 1690.5781 | AQ198: 1684.2923 | AR198: 1679.8359 | AS198: 1679.5931 | AT198: 1673.7065 | AU198: 1671.7673 | AV198: 1662.9641 | AW198: 1654.4394 | AX198: 1650.8214 | AY198: 1646.0259 | AZ198: 1645.627 | BA198: 1639.0923 | BB198: 1638.2446 | BC198: 1632.8481 | BD198: 1632.3163 | BE198: 1629.9895 | BF198: 1626.4185 | BG198: 1612.9833 | BH198: 1604.592 | BI198: 1590.5132 | BJ198: 1585.3 | BK198: 1581.679 | BL198: 1575.0687 | BM198: 1571.0589 | BN198: 1565.9268 | BO198: 1565.7013 | BP198: 1565.2656 | BQ198: 1560.4721 | BR198: 1559.5297 | BS198: 1550.4968 | BT198: 1546.9661 | BU198: 1545.4958 | BV198: 1542.2049 | BW198: 1541.5355 | BX198: 1537.1544 | BY198: 1535.3534 | BZ198: 1531.8256 | CA198: 1530.4761 | CB198: 1529.0958 | CC198: 1528.0781 | CD198: 1517.5009 | CE198: 1510.8276 | CF198: 1509.9544 | CG198: 1508.3867 | CH198: 1506.8927 | CI198: 1505.1654 | CJ198: 1500.5761 | CK198: 1495.9891 | CL198: 1491.1318 | CM198: 1490.2898 | CN198: 1485.2243 | CO198: 1480.9875 | CP198: 1477.0608 | CQ198: 1471.244 | CR198: 1462.9619 | CS198: 1458.8168 | CT198: 1443.931 | CU198: 1436.7851 | CV198: 1429.9627 | CW198: 1428.6231 | CX198: 1422.8224 | CY198: 1412.5064 | CZ198: 1412.3497 | DA198: 1403.0557 | DB198: 1401.941 | DC198: 1400.462 | DD198: 1393.985 | DE198: 1390.7083 | DF198: 1372.6226 | DG198: 1369.2936 | DH198: 1358.7911 | DI198: 1355.4341 | DJ198: 1355.2268 | DK198: 1345.9 | DL198: 1335.0895 | DM198: 1328.4092 | DN198: 1326.6893 | DO198: 1324.0872 | DP198: 1323.3709 | DQ198: 1304.5091 | DR198: 1296.5601 | DS198: 1293.1678 | DT198: 1292.4326 | DU198: 1292.2171 | DV198: 1279.1055 | DW198: 1276.8661 | DX198: 1267.0758 | DY198: 1266.0094 | DZ198: 1238.0786 | EA198: 1237.9862 | EB198: 1204.0088 | EC198: 1180.0096 | ED198: 1177.2296 | EE198: 1092.3222 | EF198: 1079.6065 | EG198: 1053.9088 | EH198: 1043.3514 | EI198: 1035.6214 | EJ198: 763.78079

Sheet efficiencies
A1: skip
A3: Module efficiencies
A5: source | B5: https://treeze.ch/fileadmin/user_upload/downloads/Publications/Case_Studies/Energy/Future-PV-LCA-IEA-PVPS-Task-12-March-2015.pdf
A6: year | B6: 2015
A8: % module efficiency | B8: Single-Si | C8: CdTe
A9: today | B9: 15.1 | C9: 20.5
A10: 2030-2050 | B10: 25.2 | C10: 22.6
A12: source | B12: https://www.psi.ch/sites/default/files/import/ta/PublicationTab/Final-Report-BFE-Project.pdf
A13: year | B13: 2017
A15: % module efficiency | B15: Single-Si | C15: Multi-Si | D15: CdTe
A16: Best today | B16: 21.5 | C16: 17 | D16: 17
A17: 2050 | B17: 27 | C17: 27 | D17: 27
A19: source | B19: https://www.ise.fraunhofer.de/content/dam/ise/de/documents/publications/studies/Photovoltaics-Report.pdf
A20: year | B20: 2021
A22: % module efficiency | B22: Single-Si | C22: Multi-Si | D22: CIGS | E22: CdTe | F22: Perovskite
A23: Record lab | B23: 26.7 | C23: 24.4 | D23: 23.4 | E23: 21 | F23: 25.5
A25: source | B25: https://www.science.org/doi/10.1126/science.aad4424
A26: year | B26: 2016
A28: % module efficiency | B28: micro-Si | C28: CdTe | D28: Perovskite
A29: 2004 | B29: 20
A30: 2011 | C30: 16
A31: 2013 | D31: 13.5
A32: 2016 | B32: 21 | C32: 21 | D32: 20.5
A34: source | B34: https://iea.blob.core.windows.net/assets/3a99654f-ffff-469f-b83c-bf0386ed8537/pv_roadmap.pdf
A35: year | B35: 2010
B37: sc-Si | C37: mc-Si | D37: a-Si | E37: CdTe | F37: CIS/CIGS
A38: current | B38: 14 - 20 | C38: 13 - 15 | D38: 6 - 9 | E38: 9 - 11 | F38: 10 - 12
A40: % module efficiency | B40: single-Si | C40: multi-Si | D40: thin film | E40: CIGS | F40: CdTe
A41: 2010 | B41: 21 | C41: 17 | D41: 10 | E41: 14 | F41: 12
A42: 2020 | B42: 23 | C42: 19 | D42: 12 | E42: 15 | F42: 14
A43: 2050 | B43: 25 | C43: 21 | D43: 15 | E43: 18 | F43: 15
Q45: technology | R45: year | S45: efficiency
A46: Synthesis | Q46: micro-Si | R46: 2010 | S46: 0.1
A47: % module efficiency | B47: a-Si | C47: ribbon-Si | D47: micro-Si | E47: single-Si | F47: multi-Si | G47: CIGS | H47: CIS | I47: CdTe | Q47: single-Si | R47: 2010 | S47: 0.151
A48: 2005 | Q48: multi-Si | R48: 2010 | S48: 0.14
A49: 2010 | D49: 10 | E49: 15.1 | F49: 14 | G49: 11 | H49: 11 | I49: 10 | Q49: CIGS | R49: 2010 | S49: 0.11
A50: 2020 | D50: 11.9 | E50: 17.9 | F50: 16.8 | G50: 14 | H50: 14 | I50: 16.8 | Q50: CIS | R50: 2010 | S50: 0.11
A51: 2050 | D51: 12.5 | E51: 26.7 | F51: 24.4 | G51: 23.4 | H51: 23.4 | I51: 21 | Q51: CdTe | R51: 2010 | S51: 0.1
Q52: micro-Si | R52: 2020 | S52: 0.119
Q53: single-Si | R53: 2020 | S53: 0.179
B54: https://iopscience.iop.org/article/10.7567/APEX.11.022301 | Q54: multi-Si | R54: 2020 | S54: 0.168
B55: https://treeze.ch/fileadmin/user_upload/downloads/Publications/Case_Studies/Energy/Future-PV-LCA-IEA-PVPS-Task-12-March-2015.pdf | Q55: CIGS | R55: 2020 | S55: 0.14
B56: https://www.ise.fraunhofer.de/content/dam/ise/de/documents/publications/studies/Photovoltaics-Report.pdf | Q56: CIS | R56: 2020 | S56: 0.14
B57: Fraunhofer ISE Photovoltaics Report 2019 | Q57: CdTe | R57: 2020 | S57: 0.168
B58: https://iea.blob.core.windows.net/assets/3a99654f-ffff-469f-b83c-bf0386ed8537/pv_roadmap.pdf | Q58: micro-Si | R58: 2050 | S58: 0.125
B59: Numbers/technologies used in electricity markets. | Q59: single-Si | R59: 2050 | S59: 0.267
Q60: multi-Si | R60: 2050 | S60: 0.244
Q61: CIGS | R61: 2050 | S61: 0.234
Q62: CIS | R62: 2050 | S62: 0.234
Q63: CdTe | R63: 2050 | S63: 0.21

Sheet extension - productivity
A1: skip
A2: source | B2: https://globalsolaratlas.info/download/world
B3: This provides yearly production per kWp installed, per country.
B4: This follows the method used in the IEA PVPS 2020 report.
A6: ISO_A2 | B6: Country | C6: PVOUT_kWh_per_kWp_yr
A7: NA | B7: Namibia | C7: 1979.0093
A8: EG | B8: Egypt | C8: 1958.4458
A9: JO | B9: Jordan | C9: 1946.616
A10: LY | B10: Libya | C10: 1942.5185
A11: YE | B11: Yemen | C11: 1914.3523
A12: SA | B12: Saudi Arabia | C12: 1895.5329
A13: EH | B13: Western Sahara | C13: 1894.9715
A14: BW | B14: Botswana | C14: 1894.5763
A15: OM | B15: Oman | C15: 1888.512
A16: DZ | B16: Algeria | C16: 1874.3373
A17: -99 | B17: Somaliland | C17: 1869.6603
A18: SD | B18: Sudan | C18: 1862.6667
A19: LS | B19: Lesotho | C19: 1858.0166
A20: MA | B20: Morocco | C20: 1845.8179
A21: NE | B21: Niger | C21: 1844.0493
A22: IL | B22: Israel | C22: 1842.419
A23: ZA | B23: South Africa | C23: 1840.1733
A24: TD | B24: Chad | C24: 1834.9098
A25: AE | B25: United Arab Emirates | C25: 1831.0609
A26: AU | B26: Australia | C26: 1822.2432
A27: AF | B27: Afghanistan | C27: 1821.0703
A28: MR | B28: Mauritania | C28: 1806.0932
A29: QA | B29: Qatar | C29: 1797.0891
... A47: ET | B47: Ethiopia | C47: 1711.3513
A48: -99 | B48: Turkish Republic of Northern Cyprus | C48: 1709.3911
A49: CY | B49: Cyprus | C49: 1706.4762
A50: PK | B50: Pakistan | C50: 1704.3105
A51: SO | B51: Somalia | C51: 1690.755
A52: MW | B52: Malawi | C52: 1690.5781
A53: SN | B53: Senegal | C53: 1684.2923
A54: BF | B54: Burkina Faso | C54: 1679.8359
A55: GM | B55: The Gambia | C55: 1679.5931
A56: HT | B56: Haiti | C56: 1673.7065
A57: AR | B57: Argentina | C57: 1671.7673
A58: KE | B58: Kenya | C58: 1662.9641
A59: TZ | B59: Tanzania | C59: 1654.4394
A60: CU | B60: Cuba | C60: 1650.8214
... A135: ID | B135: Indonesia | C135: 1355.2268
A136: -99 | B136: Kosovo | C136: 1350.7575
A137: NC | B137: New Caledonia | C137: 1345.9
A138: PG | B138: Papua New Guinea | C138: 1335.0895
A139: GQ | B139: Equatorial Guinea | C139: 1328.4092
A140: GA | B140: Gabon | C140: 1326.6893
A141: HR | B141: Croatia | C141: 1324.0872
A142: GE | B142: Georgia | C142: 1323.3709
A143: SB | B143: Solomon Islands | C143: 1304.5091
A144: RS | B144: Serbia | C144: 1296.5601
A145: FJ | B145: Fiji | C145: 1293.1678
A146: BA | B146: Bosnia and Herzegovina | C146: 1292.4326
A147: VU | B147: Vanuatu | C147: 1292.2171
A148: CA | B148: Canada | C148: 1291.6493
... A152: HU | B152: Hungary | C152: 1268.7847
A153: -99 | B153: France | C153: 1267.6574
A154: VN | B154: Vietnam | C154: 1267.0758
A155: MD | B155: Moldova | C155: 1266.0094
A156: SI | B156: Slovenia | C156: 1238.0786
A157: EC | B157: Ecuador | C157: 1237.9862
A158: CH | B158: Switzerland | C158: 1236.5467
A159: JP | B159: Japan | C159: 1235.4358
A160: UA | B160: Ukraine | C160: 1204.0088
A161: SK | B161: Slovakia | C161: 1180.0096
A162: FK | B162: Falkland Islands | C162: 1177.2296
A163: AT | B163: Austria | C163: 1174.892
A164: CZ | B164: Czech Republic | C164: 1117.056
A165: PL | B165: Poland | C165: 1092.3222
... A177: GB | B177: United Kingdom | C177: 949.1316
A178: -99 | B178: Norway | C178: 937.32085
A179: IE | B179: Ireland | C179: 919.01445
A180: RU | B180: Russia | C180: 763.78079
A181: TF | B181: French Southern and Antarctic Lands | C181: 0
A182: IS | B182: Iceland | C182: 0

Sheet extension - production vol
A1: skip
A2: Source | B2: https://www.irena.org/Publications/2025/Jul/Renewable-energy-statistics-2025
B3: These are production volumes, from photovoltaic PV.
A5: Country | B5: ISO2 | C5: Year | D5: Electricity Generation (GWh)
A6: Afghanistan | B6: AF | C6: 2024 | D6: 39.171
A7: Albania | B7: AL | C7: 2024 | D7: 297.459
A8: Algeria | B8: DZ | C8: 2024 | D8: 85
A9: American Samoa | B9: AS | C9: 2024 | D9: 2.264
A10: Andorra | B10: AD | C10: 2024 | D10: 4.267
A11: Angola | B11: AO | C11: 2024 | D11: 2.073
A12: Anguilla | B12: AI | C12: 2024 | D12: 3.815
A13: Antigua and Barbuda | B13: AG | C13: 2024 | D13: 23.326
A14: Argentina | B14: AR | C14: 2024 | D14: 12.594
A15: Armenia | B15: AM | C15: 2024 | D15: 733.4
A16: Aruba | B16: AW | C16: 2024 | D16: 25.996
A17: Australia | B17: AU | C17: 2024 | D17: 41964.6
... A48: China, Hong Kong Special Administrative Region | B48: HK | C48: 2024 | D48: 210.23
A49: Chinese Taipei | C49: 2024 | D49: 12908.69
A50: Colombia | B50: CO | C50: 2024 | D50: 29
A51: Comoros (the) | B51: KM | C51: 2024 | D51: 0.1
A52: Congo (the) | B52: CG | C52: 2024 | D52: 0.951
A53: Cook Islands (the) | B53: CK | C53: 2024 | D53: 2.598
A54: Costa Rica | B54: CR | C54: 2024 | D54: 2.542
A55: Croatia | B55: HR | C55: 2024 | D55: 413.1
A56: Cuba | B56: CU | C56: 2024 | D56: 12.389
A57: Cura√ßao | B57: CW | C57: 2024 | D57: 0.007
A58: Cyprus | B58: CY | C58: 2024 | D58: 830.523
A59: Czechia | B59: CZ | C59: 2024 | D59: 2892.093
A60: C√¥te d'Ivoire | B60: CI | C60: 2024 | D60: 13.1
A61: Democratic People's Republic of Korea (the) | B61: KP | C61: 2024 | D61: 166.651
... A114: Kuwait | B114: KW | C114: 2024 | D114: 57.174
A115: Kyrgyzstan | B115: KG | C115: 2024
A116: Lao People's Democratic Republic (the) | B116: LA | C116: 2024 | D116: 0.468
A117: Latvia | B117: LV | C117: 2024 | D117: 239.068
A118: Lebanon | B118: LB | C118: 2024 | D118: 0.801
A119: Lesotho | B119: LS | C119: 2024 | D119: 0.89
A120: Liberia | B120: LR | C120: 2024 | D120: 4.034
A121: Libya | B121: LY | C121: 2024 | D121: 7.791
A122: Lithuania | B122: LT | C122: 2024 | D122: 608.7
A123: Luxembourg | B123: LU | C123: 2024 | D123: 293.959
A124: Madagascar | B124: MG | C124: 2024 | D124: 14.169
A125: Malawi | B125: MW | C125: 2024 | D125: 11.923
A126: Malaysia | B126: MY | C126: 2024 | D126: 9.961
A127: Maldives | B127: MV | C127: 2024 | D127: 82.5
... A129: Malta | B129: MT | C129: 2024 | D129: 308.963
A130: Marshall Islands (the) | C130: 2024 | D130: 0.98
A131: Martinique | B131: MQ | C131: 2024 | D131: 107.523
A132: Mauritania | B132: MR | C132: 2024 | D132: 88
A133: Mauritius | B133: MU | C133: 2024 | D133: 2.496
A134: Mayotte | B134: YT | C134: 2024 | D134: 46.226
A135: Mexico | B135: MX | C135: 2024 | D135: 15.021
A136: Micronesia (Federated States of) | C136: 2024 | D136: 0.197
A137: Mongolia | B137: MN | C137: 2024 | D137: 7.795
A138: Montenegro | B138: ME | C138: 2024 | D138: 17.2
A139: Montserrat | B139: MS | C139: 2024 | D139: 1.635
A140: Morocco | B140: MA | C140: 2024 | D140: 27.6
A141: Mozambique | B141: MZ | C141: 2024 | D141: 2.142
A142: Multilateral | C142: 2022
A143: Myanmar | B143: MM | C143: 2024 | D143: 129.5
A144: Namibia | B144: NA | C144: 2024 | D144: 13.901
A145: Nauru | B145: NR | C145: 2024 | D145: 0.204
A146: Nepal | B146: NP | C146: 2024 | D146: 80.586
A147: Netherlands (Kingdom of the) | B147: NL | C147: 2024 | D147: 19578.188
A148: New Caledonia | B148: NC | C148: 2024 | D148: 0.92
A149: New Zealand | B149: NZ | C149: 2024 | D149: 370.314
A150: Nicaragua | B150: NI | C150: 2024 | D150: 4.03
A151: Niger (the) | B151: NE | C151: 2024 | D151: 17.9
A152: Nigeria | B152: NG | C152: 2024 | D152: 182.807
A153: Niue | B153: NU | C153: 2024 | D153: 0.469
A154: North Macedonia | B154: MK | C154: 2024 | D154: 355.474
... A169: Republic of Moldova (the) | B169: MD | C169: 2024 | D169: 132.3
A170: Residual/unallocated ODA: Central Asia and Southern Asia | C170: 2023
A171: Residual/unallocated ODA: Eastern and South-eastern Asia | C171: 2023
A172: Residual/unallocated ODA: Latin America and the Caribbean | C172: 2023
A173: Residual/unallocated ODA: Northern America and Europe | C173: 2022
A174: Residual/unallocated ODA: Oceania excl. Aus. and N. Zealand | C174: 2022
A175: Residual/unallocated ODA: Sub-Saharan Africa | C175: 2023
A176: Residual/unallocated ODA: Western Asia¬†and Northern Africa | C176: 2023
A177: Romania | B177: RO | C177: 2024 | D177: 2227.05
A178: Russian Federation (the) | B178: RU | C178: 2024 | D178: 3224.036
A179: Rwanda | B179: RW | C179: 2024 | D179: 21.59
A180: R√©union | B180: RE | C180: 2024 | D180: 2.281
A181: Saint Barth√©lemy | B181: BL | C181: 2024 | D181: 0.09
A182: Saint Kitts and Nevis | B182: KN | C182: 2024 | D182: 0.002
A183: Saint Lucia | B183: LC | C183: 2024 | D183: 8.276
A184: Saint Martin (French Part) | B184: MF | C184: 2024 | D184: 1.646
A185: Saint Vincent and the Grenadines | B185: VC | C185: 2024 | D185: 7.464
A186: Samoa | B186: WS | C186: 2024 | D186: 0.004
A187: Sao Tome and Principe | B187: ST | C187: 2024 | D187: 0.013
A188: Saudi Arabia | B188: SA | C188: 2024 | D188: 4797
... A207: Syrian Arab Republic (the) | B207: SY | C207: 2024 | D207: 102.1
A208: Tajikistan | B208: TJ | C208: 2024
A209: Thailand | B209: TH | C209: 2024 | D209: 26.284
A210: Timor-Leste | B210: TL | C210: 2024 | D210: 0.142
A211: Togo | B211: TG | C211: 2024 | D211: 76.959
A212: Tokelau | B212: TK | C212: 2024 | D212: 0.022
A213: Tonga | B213: TO | C213: 2024 | D213: 0.594
A214: Trinidad and Tobago | B214: TT | C214: 2024 | D214: 6.228
A215: Tunisia | B215: TN | C215: 2024 | D215: 16
A216: Turkmenistan | B216: TM | C216: 2024 | D216: 0.196
...
